{"NIC.1_1":{"FOI":{"mean":0.0244,"sd":0.0023},"serop9":{"mean":41.6941,"sd":3.7298}},"NIC.2_1":{"FOI":{"mean":0.0242,"sd":0.0027},"serop9":{"mean":42.0627,"sd":4.3178}},"NIC.3_1":{"FOI":{"mean":0.0272,"sd":0.0025},"serop9":{"mean":37.7394,"sd":3.6412}},"NIC.4_1":{"FOI":{"mean":0.0314,"sd":0.0027},"serop9":{"mean":32.4514,"sd":3.5477}},"NIC.5_1":{"FOI":{"mean":0.0292,"sd":0.0019},"serop9":{"mean":35.0407,"sd":2.6402}},"NIC.6_1":{"FOI":{"mean":0.027,"sd":0.0026},"serop9":{"mean":37.9422,"sd":3.7763}},"NIC.7_1":{"FOI":{"mean":0.0292,"sd":0.0031},"serop9":{"mean":35.2065,"sd":4.2038}},"NIC.8_1":{"FOI":{"mean":0.0295,"sd":0.0027},"serop9":{"mean":34.7429,"sd":3.6701}},"NIC.9_1":{"FOI":{"mean":0.0236,"sd":0.0027},"serop9":{"mean":42.9572,"sd":4.4659}},"NIC.10_1":{"FOI":{"mean":0.0266,"sd":0.0022},"serop9":{"mean":38.5186,"sd":3.2905}},"NIC.11_1":{"FOI":{"mean":0.0309,"sd":0.0023},"serop9":{"mean":32.9984,"sd":3.0465}},"NIC.12_1":{"FOI":{"mean":0.0299,"sd":0.0033},"serop9":{"mean":34.3868,"sd":4.3678}},"NIC.13_1":{"FOI":{"mean":0.03,"sd":0.002},"serop9":{"mean":33.9956,"sd":2.6734}},"NIC.14_1":{"FOI":{"mean":0.0311,"sd":0.0021},"serop9":{"mean":32.7743,"sd":2.8229}},"NIC.15_1":{"FOI":{"mean":0.0266,"sd":0.0025},"serop9":{"mean":38.5197,"sd":3.7232}},"NIC.16_1":{"FOI":{"mean":0.0263,"sd":0.0036},"serop9":{"mean":39.0792,"sd":5.2971}},"NIC.17_1":{"FOI":{"mean":0.0252,"sd":0.0026},"serop9":{"mean":40.5996,"sd":4.0418}},"NIC.18_1":{"FOI":{"mean":0.0302,"sd":0.0025},"serop9":{"mean":33.893,"sd":3.4612}}}
