{"SLV.1_1":{"FOI":{"mean":0.0316,"sd":0},"serop9":{"mean":32.1701,"sd":0}},"SLV.2_1":{"FOI":{"mean":0.0316,"sd":0},"serop9":{"mean":32.1289,"sd":0}},"SLV.3_1":{"FOI":{"mean":0.0298,"sd":0},"serop9":{"mean":34.2476,"sd":0}},"SLV.4_1":{"FOI":{"mean":0.0313,"sd":0},"serop9":{"mean":32.5932,"sd":0}},"SLV.5_1":{"FOI":{"mean":0.0322,"sd":0},"serop9":{"mean":31.4656,"sd":0}},"SLV.6_1":{"FOI":{"mean":0.0337,"sd":0},"serop9":{"mean":29.8084,"sd":0}},"SLV.7_1":{"FOI":{"mean":0.0324,"sd":0},"serop9":{"mean":31.1684,"sd":0}},"SLV.8_1":{"FOI":{"mean":0.0321,"sd":0},"serop9":{"mean":31.6254,"sd":0}},"SLV.9_1":{"FOI":{"mean":0.0314,"sd":0},"serop9":{"mean":32.3337,"sd":0}},"SLV.10_1":{"FOI":{"mean":0.0326,"sd":0},"serop9":{"mean":31.1026,"sd":0}},"SLV.11_1":{"FOI":{"mean":0.0318,"sd":0},"serop9":{"mean":31.9275,"sd":0}},"SLV.12_1":{"FOI":{"mean":0.0301,"sd":0},"serop9":{"mean":34.0297,"sd":0}},"SLV.13_1":{"FOI":{"mean":0.0317,"sd":0},"serop9":{"mean":32.1329,"sd":0}},"SLV.14_1":{"FOI":{"mean":0.0329,"sd":0},"serop9":{"mean":30.6986,"sd":0}}}
