{"IDN.1.1_1":{"FOI":{"mean":0.028,"sd":0},"serop9":{"mean":36.5647,"sd":0}},"IDN.1.10_1":{"FOI":{"mean":0.0295,"sd":0},"serop9":{"mean":34.6491,"sd":0}},"IDN.1.11_1":{"FOI":{"mean":0.031,"sd":0},"serop9":{"mean":32.8421,"sd":0}},"IDN.1.12_1":{"FOI":{"mean":0.0324,"sd":0},"serop9":{"mean":31.2801,"sd":0}},"IDN.1.13_1":{"FOI":{"mean":0.0285,"sd":0},"serop9":{"mean":35.964,"sd":0}},"IDN.1.14_1":{"FOI":{"mean":0.0328,"sd":0},"serop9":{"mean":30.8726,"sd":0}},"IDN.1.15_1":{"FOI":{"mean":0.0245,"sd":0},"serop9":{"mean":41.6631,"sd":0}},"IDN.1.16_1":{"FOI":{"mean":0.0271,"sd":0},"serop9":{"mean":37.8259,"sd":0}},"IDN.1.17_1":{"FOI":{"mean":0.031,"sd":0},"serop9":{"mean":32.8421,"sd":0}},"IDN.1.18_1":{"FOI":{"mean":0.0292,"sd":0},"serop9":{"mean":35.111,"sd":0}},"IDN.1.19_1":{"FOI":{"mean":0.0318,"sd":0},"serop9":{"mean":31.9526,"sd":0}},"IDN.1.2_1":{"FOI":{"mean":0.0286,"sd":0},"serop9":{"mean":35.8369,"sd":0}},"IDN.1.20_1":{"FOI":{"mean":0.0314,"sd":0},"serop9":{"mean":32.4668,"sd":0}},"IDN.1.21_1":{"FOI":{"mean":0.027,"sd":0},"serop9":{"mean":38.0202,"sd":0}},"IDN.1.22_1":{"FOI":{"mean":0.0277,"sd":0},"serop9":{"mean":37.067,"sd":0}},"IDN.1.23_1":{"FOI":{"mean":0.0305,"sd":0},"serop9":{"mean":33.4898,"sd":0}},"IDN.1.3_1":{"FOI":{"mean":0.0324,"sd":0},"serop9":{"mean":31.2801,"sd":0}},"IDN.1.4_1":{"FOI":{"mean":0.0289,"sd":0},"serop9":{"mean":35.4351,"sd":0}},"IDN.1.5_1":{"FOI":{"mean":0.0278,"sd":0},"serop9":{"mean":36.9016,"sd":0}},"IDN.1.6_1":{"FOI":{"mean":0.0301,"sd":0},"serop9":{"mean":33.9306,"sd":0}},"IDN.1.7_1":{"FOI":{"mean":0.0317,"sd":0},"serop9":{"mean":32.033,"sd":0}},"IDN.1.8_1":{"FOI":{"mean":0.025,"sd":0},"serop9":{"mean":40.88,"sd":0}},"IDN.1.9_1":{"FOI":{"mean":0.029,"sd":0},"serop9":{"mean":35.3219,"sd":0}},"IDN.10.1_1":{"FOI":{"mean":0.0276,"sd":0},"serop9":{"mean":37.2836,"sd":0}},"IDN.10.10_1":{"FOI":{"mean":0.0394,"sd":0},"serop9":{"mean":25.2183,"sd":0}},"IDN.10.11_1":{"FOI":{"mean":0.0343,"sd":0},"serop9":{"mean":29.3251,"sd":0}},"IDN.10.12_1":{"FOI":{"mean":0.0273,"sd":0},"serop9":{"mean":37.6291,"sd":0}},"IDN.10.13_1":{"FOI":{"mean":0.0361,"sd":0},"serop9":{"mean":27.6391,"sd":0}},"IDN.10.14_1":{"FOI":{"mean":0.0333,"sd":0},"serop9":{"mean":30.5758,"sd":0}},"IDN.10.15_1":{"FOI":{"mean":0.0286,"sd":0},"serop9":{"mean":36.0041,"sd":0}},"IDN.10.16_1":{"FOI":{"mean":0.0448,"sd":0},"serop9":{"mean":20.4024,"sd":0}},"IDN.10.17_1":{"FOI":{"mean":0.0401,"sd":0},"serop9":{"mean":23.8808,"sd":0}},"IDN.10.18_1":{"FOI":{"mean":0.0554,"sd":0},"serop9":{"mean":15.7132,"sd":0}},"IDN.10.19_1":{"FOI":{"mean":0.0294,"sd":0},"serop9":{"mean":35.0982,"sd":0}},"IDN.10.2_1":{"FOI":{"mean":0.0294,"sd":0},"serop9":{"mean":34.8836,"sd":0}},"IDN.10.20_1":{"FOI":{"mean":0.0286,"sd":0},"serop9":{"mean":36.0041,"sd":0}},"IDN.10.21_1":{"FOI":{"mean":0.029,"sd":0},"serop9":{"mean":35.4842,"sd":0}},"IDN.10.22_1":{"FOI":{"mean":0.0448,"sd":0},"serop9":{"mean":20.4024,"sd":0}},"IDN.10.23_1":{"FOI":{"mean":0.0456,"sd":0},"serop9":{"mean":19.9194,"sd":0}},"IDN.10.24_1":{"FOI":{"mean":0.0298,"sd":0},"serop9":{"mean":34.4176,"sd":0}},"IDN.10.25_1":{"FOI":{"mean":0.0279,"sd":0},"serop9":{"mean":36.8625,"sd":0}},"IDN.10.26_1":{"FOI":{"mean":0.0289,"sd":0},"serop9":{"mean":35.6805,"sd":0}},"IDN.10.27_1":{"FOI":{"mean":0.0308,"sd":0},"serop9":{"mean":33.3637,"sd":0}},"IDN.10.28_1":{"FOI":{"mean":0.0307,"sd":0},"serop9":{"mean":33.5334,"sd":0}},"IDN.10.29_1":{"FOI":{"mean":0.0337,"sd":0},"serop9":{"mean":30.0793,"sd":0}},"IDN.10.3_1":{"FOI":{"mean":0.0361,"sd":0},"serop9":{"mean":27.5808,"sd":0}},"IDN.10.30_1":{"FOI":{"mean":0.0367,"sd":0},"serop9":{"mean":27.0337,"sd":0}},"IDN.10.31_1":{"FOI":{"mean":0.0367,"sd":0},"serop9":{"mean":27.0337,"sd":0}},"IDN.10.32_1":{"FOI":{"mean":0.0554,"sd":0},"serop9":{"mean":15.7132,"sd":0}},"IDN.10.33_1":{"FOI":{"mean":0.0354,"sd":0},"serop9":{"mean":28.3827,"sd":0}},"IDN.10.34_1":{"FOI":{"mean":0.0282,"sd":0},"serop9":{"mean":36.5484,"sd":0}},"IDN.10.35_1":{"FOI":{"mean":0.0312,"sd":0},"serop9":{"mean":32.7805,"sd":0}},"IDN.10.36_1":{"FOI":{"mean":0.0246,"sd":0},"serop9":{"mean":41.3589,"sd":0}},"IDN.10.4_1":{"FOI":{"mean":0.0277,"sd":0},"serop9":{"mean":37.1437,"sd":0}},"IDN.10.5_1":{"FOI":{"mean":0.0298,"sd":0},"serop9":{"mean":34.5048,"sd":0}},"IDN.10.6_1":{"FOI":{"mean":0.0474,"sd":0},"serop9":{"mean":18.7991,"sd":0}},"IDN.10.7_1":{"FOI":{"mean":0.0322,"sd":0},"serop9":{"mean":31.701,"sd":0}},"IDN.10.8_1":{"FOI":{"mean":0.0302,"sd":0},"serop9":{"mean":34.0765,"sd":0}},"IDN.10.9_1":{"FOI":{"mean":0.0282,"sd":0},"serop9":{"mean":36.5484,"sd":0}},"IDN.11.1_1":{"FOI":{"mean":0.0285,"sd":0},"serop9":{"mean":36.0918,"sd":0}},"IDN.11.10_1":{"FOI":{"mean":0.0396,"sd":0},"serop9":{"mean":24.2433,"sd":0}},"IDN.11.11_1":{"FOI":{"mean":0.0316,"sd":0},"serop9":{"mean":32.2219,"sd":0}},"IDN.11.12_1":{"FOI":{"mean":0.0414,"sd":0},"serop9":{"mean":22.6989,"sd":0}},"IDN.11.13_1":{"FOI":{"mean":0.0306,"sd":0},"serop9":{"mean":33.7909,"sd":0}},"IDN.11.14_1":{"FOI":{"mean":0.0286,"sd":0},"serop9":{"mean":36.0165,"sd":0}},"IDN.11.15_1":{"FOI":{"mean":0.0405,"sd":0},"serop9":{"mean":24.2334,"sd":0}},"IDN.11.16_1":{"FOI":{"mean":0.0346,"sd":0},"serop9":{"mean":29.1099,"sd":0}},"IDN.11.17_1":{"FOI":{"mean":0.0388,"sd":0},"serop9":{"mean":25.1127,"sd":0}},"IDN.11.18_1":{"FOI":{"mean":0.0302,"sd":0},"serop9":{"mean":33.9617,"sd":0}},"IDN.11.19_1":{"FOI":{"mean":0.0295,"sd":0},"serop9":{"mean":34.7828,"sd":0}},"IDN.11.2_1":{"FOI":{"mean":0.0307,"sd":0},"serop9":{"mean":33.2767,"sd":0}},"IDN.11.20_1":{"FOI":{"mean":0.0306,"sd":0},"serop9":{"mean":33.7909,"sd":0}},"IDN.11.21_1":{"FOI":{"mean":0.0366,"sd":0},"serop9":{"mean":27.1413,"sd":0}},"IDN.11.22_1":{"FOI":{"mean":0.0302,"sd":0},"serop9":{"mean":33.9225,"sd":0}},"IDN.11.23_1":{"FOI":{"mean":0.0405,"sd":0},"serop9":{"mean":24.2334,"sd":0}},"IDN.11.24_1":{"FOI":{"mean":0.0393,"sd":0},"serop9":{"mean":24.7039,"sd":0}},"IDN.11.25_1":{"FOI":{"mean":0.0315,"sd":0},"serop9":{"mean":32.5777,"sd":0}},"IDN.11.26_1":{"FOI":{"mean":0.0321,"sd":0},"serop9":{"mean":31.6452,"sd":0}},"IDN.11.27_1":{"FOI":{"mean":0.0292,"sd":0},"serop9":{"mean":35.2758,"sd":0}},"IDN.11.28_1":{"FOI":{"mean":0.0346,"sd":0},"serop9":{"mean":29.1099,"sd":0}},"IDN.11.29_1":{"FOI":{"mean":0.0328,"sd":0},"serop9":{"mean":30.972,"sd":0}},"IDN.11.3_1":{"FOI":{"mean":0.0128,"sd":0},"serop9":{"mean":63.3663,"sd":0}},"IDN.11.30_1":{"FOI":{"mean":0.0388,"sd":0},"serop9":{"mean":25.1127,"sd":0}},"IDN.11.31_1":{"FOI":{"mean":0.0281,"sd":0},"serop9":{"mean":36.595,"sd":0}},"IDN.11.32_1":{"FOI":{"mean":0.0363,"sd":0},"serop9":{"mean":27.6892,"sd":0}},"IDN.11.33_1":{"FOI":{"mean":0.0319,"sd":0},"serop9":{"mean":31.9499,"sd":0}},"IDN.11.34_1":{"FOI":{"mean":0.0299,"sd":0},"serop9":{"mean":34.4258,"sd":0}},"IDN.11.35_1":{"FOI":{"mean":0.0327,"sd":0},"serop9":{"mean":31.4083,"sd":0}},"IDN.11.36_1":{"FOI":{"mean":0.0278,"sd":0},"serop9":{"mean":36.8475,"sd":0}},"IDN.11.37_1":{"FOI":{"mean":0.0284,"sd":0},"serop9":{"mean":36.321,"sd":0}},"IDN.11.38_1":{"FOI":{"mean":0.0316,"sd":0},"serop9":{"mean":32.2151,"sd":0}},"IDN.11.4_1":{"FOI":{"mean":0.0316,"sd":0},"serop9":{"mean":32.2219,"sd":0}},"IDN.11.5_1":{"FOI":{"mean":0.0318,"sd":0},"serop9":{"mean":32.3192,"sd":0}},"IDN.11.6_1":{"FOI":{"mean":0.0276,"sd":0},"serop9":{"mean":37.2746,"sd":0}},"IDN.11.7_1":{"FOI":{"mean":0.0353,"sd":0},"serop9":{"mean":28.565,"sd":0}},"IDN.11.8_1":{"FOI":{"mean":0.0296,"sd":0},"serop9":{"mean":34.6534,"sd":0}},"IDN.11.9_1":{"FOI":{"mean":0.0339,"sd":0},"serop9":{"mean":30.0149,"sd":0}},"IDN.12.1_1":{"FOI":{"mean":0.0318,"sd":0},"serop9":{"mean":31.9973,"sd":0}},"IDN.12.10_1":{"FOI":{"mean":0.0351,"sd":0},"serop9":{"mean":28.3606,"sd":0}},"IDN.12.11_1":{"FOI":{"mean":0.0306,"sd":0},"serop9":{"mean":33.4721,"sd":0}},"IDN.12.12_1":{"FOI":{"mean":0.0295,"sd":0},"serop9":{"mean":34.7761,"sd":0}},"IDN.12.13_1":{"FOI":{"mean":0.0335,"sd":0},"serop9":{"mean":30.0468,"sd":0}},"IDN.12.14_1":{"FOI":{"mean":0.0286,"sd":0},"serop9":{"mean":35.855,"sd":0}},"IDN.12.2_1":{"FOI":{"mean":0.0283,"sd":0},"serop9":{"mean":36.2897,"sd":0}},"IDN.12.3_1":{"FOI":{"mean":0.0269,"sd":0},"serop9":{"mean":38.0842,"sd":0}},"IDN.12.4_1":{"FOI":{"mean":0.0266,"sd":0},"serop9":{"mean":38.535,"sd":0}},"IDN.12.5_1":{"FOI":{"mean":0.0325,"sd":0},"serop9":{"mean":31.1175,"sd":0}},"IDN.12.6_1":{"FOI":{"mean":0.0349,"sd":0},"serop9":{"mean":28.5755,"sd":0}},"IDN.12.7_1":{"FOI":{"mean":0.0291,"sd":0},"serop9":{"mean":35.3017,"sd":0}},"IDN.12.8_1":{"FOI":{"mean":0.0299,"sd":0},"serop9":{"mean":34.2939,"sd":0}},"IDN.12.9_1":{"FOI":{"mean":0.0301,"sd":0},"serop9":{"mean":34.0016,"sd":0}},"IDN.13.1_1":{"FOI":{"mean":0.0316,"sd":0},"serop9":{"mean":32.2824,"sd":0}},"IDN.13.10_1":{"FOI":{"mean":0.0307,"sd":0},"serop9":{"mean":33.2934,"sd":0}},"IDN.13.11_1":{"FOI":{"mean":0.032,"sd":0},"serop9":{"mean":31.7304,"sd":0}},"IDN.13.12_1":{"FOI":{"mean":0.0328,"sd":0},"serop9":{"mean":30.8285,"sd":0}},"IDN.13.13_1":{"FOI":{"mean":0.0319,"sd":0},"serop9":{"mean":31.8846,"sd":0}},"IDN.13.2_1":{"FOI":{"mean":0.031,"sd":0},"serop9":{"mean":32.8266,"sd":0}},"IDN.13.3_1":{"FOI":{"mean":0.0297,"sd":0},"serop9":{"mean":34.4922,"sd":0}},"IDN.13.4_1":{"FOI":{"mean":0.0322,"sd":0},"serop9":{"mean":31.4934,"sd":0}},"IDN.13.5_1":{"FOI":{"mean":0.0322,"sd":0},"serop9":{"mean":31.4934,"sd":0}},"IDN.13.6_1":{"FOI":{"mean":0.0316,"sd":0},"serop9":{"mean":32.1822,"sd":0}},"IDN.13.7_1":{"FOI":{"mean":0.0319,"sd":0},"serop9":{"mean":31.8955,"sd":0}},"IDN.13.8_1":{"FOI":{"mean":0.0316,"sd":0},"serop9":{"mean":32.2115,"sd":0}},"IDN.13.9_1":{"FOI":{"mean":0.0333,"sd":0},"serop9":{"mean":30.2478,"sd":0}},"IDN.14.1_1":{"FOI":{"mean":0.0302,"sd":0},"serop9":{"mean":33.9371,"sd":0}},"IDN.14.10_1":{"FOI":{"mean":0.0243,"sd":0},"serop9":{"mean":41.9105,"sd":0}},"IDN.14.11_1":{"FOI":{"mean":0.0327,"sd":0},"serop9":{"mean":31.0689,"sd":0}},"IDN.14.12_1":{"FOI":{"mean":0.0284,"sd":0},"serop9":{"mean":36.2184,"sd":0}},"IDN.14.13_1":{"FOI":{"mean":0.0255,"sd":0},"serop9":{"mean":40.1584,"sd":0}},"IDN.14.14_1":{"FOI":{"mean":0.0266,"sd":0},"serop9":{"mean":38.553,"sd":0}},"IDN.14.2_1":{"FOI":{"mean":0.0297,"sd":0},"serop9":{"mean":34.6257,"sd":0}},"IDN.14.3_1":{"FOI":{"mean":0.0281,"sd":0},"serop9":{"mean":36.6719,"sd":0}},"IDN.14.4_1":{"FOI":{"mean":0.0255,"sd":0},"serop9":{"mean":40.1321,"sd":0}},"IDN.14.5_1":{"FOI":{"mean":0.0292,"sd":0},"serop9":{"mean":35.1429,"sd":0}},"IDN.14.6_1":{"FOI":{"mean":0.0288,"sd":0},"serop9":{"mean":35.6901,"sd":0}},"IDN.14.7_1":{"FOI":{"mean":0.0278,"sd":0},"serop9":{"mean":37.0575,"sd":0}},"IDN.14.8_1":{"FOI":{"mean":0.0303,"sd":0},"serop9":{"mean":33.8337,"sd":0}},"IDN.14.9_1":{"FOI":{"mean":0.0225,"sd":0},"serop9":{"mean":44.7401,"sd":0}},"IDN.16.1_1":{"FOI":{"mean":0.0331,"sd":0},"serop9":{"mean":30.5043,"sd":0}},"IDN.16.2_1":{"FOI":{"mean":0.0336,"sd":0},"serop9":{"mean":29.924,"sd":0}},"IDN.16.3_1":{"FOI":{"mean":0.0261,"sd":0},"serop9":{"mean":39.3096,"sd":0}},"IDN.16.4_1":{"FOI":{"mean":0.0349,"sd":0},"serop9":{"mean":28.6171,"sd":0}},"IDN.16.5_1":{"FOI":{"mean":0.0299,"sd":0},"serop9":{"mean":34.1953,"sd":0}},"IDN.16.6_1":{"FOI":{"mean":0.0349,"sd":0},"serop9":{"mean":28.6171,"sd":0}},"IDN.16.7_1":{"FOI":{"mean":0.0336,"sd":0},"serop9":{"mean":29.924,"sd":0}},"IDN.17.1_1":{"FOI":{"mean":0.0366,"sd":0},"serop9":{"mean":26.9705,"sd":0}},"IDN.17.10_1":{"FOI":{"mean":0.0342,"sd":0},"serop9":{"mean":29.4033,"sd":0}},"IDN.17.11_1":{"FOI":{"mean":0.0348,"sd":0},"serop9":{"mean":28.6944,"sd":0}},"IDN.17.12_1":{"FOI":{"mean":0.0459,"sd":0},"serop9":{"mean":19.94,"sd":0}},"IDN.17.13_1":{"FOI":{"mean":0.0409,"sd":0},"serop9":{"mean":23.4076,"sd":0}},"IDN.17.14_1":{"FOI":{"mean":0.0451,"sd":0},"serop9":{"mean":20.3911,"sd":0}},"IDN.17.2_1":{"FOI":{"mean":0.0283,"sd":0},"serop9":{"mean":36.2953,"sd":0}},"IDN.17.3_1":{"FOI":{"mean":0.0323,"sd":0},"serop9":{"mean":31.3801,"sd":0}},"IDN.17.4_1":{"FOI":{"mean":0.0425,"sd":0},"serop9":{"mean":21.9767,"sd":0}},"IDN.17.5_1":{"FOI":{"mean":0.0377,"sd":0},"serop9":{"mean":26.0567,"sd":0}},"IDN.17.6_1":{"FOI":{"mean":0.0472,"sd":0},"serop9":{"mean":18.8034,"sd":0}},"IDN.17.7_1":{"FOI":{"mean":0.0363,"sd":0},"serop9":{"mean":27.4208,"sd":0}},"IDN.17.8_1":{"FOI":{"mean":0.0425,"sd":0},"serop9":{"mean":21.9767,"sd":0}},"IDN.17.9_1":{"FOI":{"mean":0.037,"sd":0},"serop9":{"mean":26.4829,"sd":0}},"IDN.18.1_1":{"FOI":{"mean":0.0304,"sd":0},"serop9":{"mean":33.5891,"sd":0}},"IDN.18.2_1":{"FOI":{"mean":0.0267,"sd":0},"serop9":{"mean":38.3712,"sd":0}},"IDN.18.3_1":{"FOI":{"mean":0.0264,"sd":0},"serop9":{"mean":38.8232,"sd":0}},"IDN.18.4_1":{"FOI":{"mean":0.0281,"sd":0},"serop9":{"mean":36.5885,"sd":0}},"IDN.18.5_1":{"FOI":{"mean":0.0315,"sd":0},"serop9":{"mean":32.3086,"sd":0}},"IDN.18.6_1":{"FOI":{"mean":0.0267,"sd":0},"serop9":{"mean":38.4494,"sd":0}},"IDN.18.7_1":{"FOI":{"mean":0.0326,"sd":0},"serop9":{"mean":31.0967,"sd":0}},"IDN.18.8_1":{"FOI":{"mean":0.0247,"sd":0},"serop9":{"mean":41.3315,"sd":0}},"IDN.18.9_1":{"FOI":{"mean":0.0272,"sd":0},"serop9":{"mean":37.808,"sd":0}},"IDN.19.1_1":{"FOI":{"mean":0.029,"sd":0},"serop9":{"mean":35.424,"sd":0}},"IDN.19.10_1":{"FOI":{"mean":0.0256,"sd":0},"serop9":{"mean":40.0222,"sd":0}},"IDN.19.11_1":{"FOI":{"mean":0.0285,"sd":0},"serop9":{"mean":36.4954,"sd":0}},"IDN.19.2_1":{"FOI":{"mean":0.027,"sd":0},"serop9":{"mean":38.0825,"sd":0}},"IDN.19.3_1":{"FOI":{"mean":0.0322,"sd":0},"serop9":{"mean":31.6086,"sd":0}},"IDN.19.4_1":{"FOI":{"mean":0.0299,"sd":0},"serop9":{"mean":34.6627,"sd":0}},"IDN.19.5_1":{"FOI":{"mean":0.025,"sd":0},"serop9":{"mean":40.7745,"sd":0}},"IDN.19.6_1":{"FOI":{"mean":0.0281,"sd":0},"serop9":{"mean":36.5412,"sd":0}},"IDN.19.7_1":{"FOI":{"mean":0.0284,"sd":0},"serop9":{"mean":36.4225,"sd":0}},"IDN.19.8_1":{"FOI":{"mean":0.0307,"sd":0},"serop9":{"mean":33.3324,"sd":0}},"IDN.19.9_1":{"FOI":{"mean":0.029,"sd":0},"serop9":{"mean":35.424,"sd":0}},"IDN.2.1_1":{"FOI":{"mean":0.0285,"sd":0},"serop9":{"mean":36.2518,"sd":0}},"IDN.2.2_1":{"FOI":{"mean":0.0253,"sd":0},"serop9":{"mean":40.3623,"sd":0}},"IDN.2.3_1":{"FOI":{"mean":0.0378,"sd":0},"serop9":{"mean":25.7703,"sd":0}},"IDN.2.4_1":{"FOI":{"mean":0.0285,"sd":0},"serop9":{"mean":36.2518,"sd":0}},"IDN.2.5_1":{"FOI":{"mean":0.0285,"sd":0},"serop9":{"mean":36.2518,"sd":0}},"IDN.2.6_1":{"FOI":{"mean":0.0357,"sd":0},"serop9":{"mean":27.8841,"sd":0}},"IDN.2.7_1":{"FOI":{"mean":0.0304,"sd":0},"serop9":{"mean":33.7152,"sd":0}},"IDN.2.8_1":{"FOI":{"mean":0.0304,"sd":0},"serop9":{"mean":33.7152,"sd":0}},"IDN.2.9_1":{"FOI":{"mean":0.0296,"sd":0},"serop9":{"mean":34.5785,"sd":0}},"IDN.20.1_1":{"FOI":{"mean":0.0278,"sd":0},"serop9":{"mean":37.0537,"sd":0}},"IDN.20.10_1":{"FOI":{"mean":0.0279,"sd":0},"serop9":{"mean":36.9256,"sd":0}},"IDN.20.2_1":{"FOI":{"mean":0.027,"sd":0},"serop9":{"mean":38.1814,"sd":0}},"IDN.20.3_1":{"FOI":{"mean":0.0281,"sd":0},"serop9":{"mean":36.5894,"sd":0}},"IDN.20.4_1":{"FOI":{"mean":0.0311,"sd":0},"serop9":{"mean":32.7385,"sd":0}},"IDN.20.5_1":{"FOI":{"mean":0.0262,"sd":0},"serop9":{"mean":39.2382,"sd":0}},"IDN.20.6_1":{"FOI":{"mean":0.0324,"sd":0},"serop9":{"mean":31.4011,"sd":0}},"IDN.20.7_1":{"FOI":{"mean":0.0361,"sd":0},"serop9":{"mean":27.4032,"sd":0}},"IDN.20.8_1":{"FOI":{"mean":0.0311,"sd":0},"serop9":{"mean":32.7385,"sd":0}},"IDN.20.9_1":{"FOI":{"mean":0.0327,"sd":0},"serop9":{"mean":31.022,"sd":0}},"IDN.21.1_1":{"FOI":{"mean":0.0303,"sd":0},"serop9":{"mean":33.7599,"sd":0}},"IDN.21.10_1":{"FOI":{"mean":0.0273,"sd":0},"serop9":{"mean":37.5912,"sd":0}},"IDN.21.11_1":{"FOI":{"mean":0.0272,"sd":0},"serop9":{"mean":37.7911,"sd":0}},"IDN.21.12_1":{"FOI":{"mean":0.0228,"sd":0},"serop9":{"mean":44.2215,"sd":0}},"IDN.21.13_1":{"FOI":{"mean":0.0258,"sd":0},"serop9":{"mean":39.9083,"sd":0}},"IDN.21.14_1":{"FOI":{"mean":0.0231,"sd":0},"serop9":{"mean":44.0112,"sd":0}},"IDN.21.15_1":{"FOI":{"mean":0.0338,"sd":0},"serop9":{"mean":29.7422,"sd":0}},"IDN.21.16_1":{"FOI":{"mean":0.0262,"sd":0},"serop9":{"mean":39.2036,"sd":0}},"IDN.21.17_1":{"FOI":{"mean":0.0243,"sd":0},"serop9":{"mean":41.9049,"sd":0}},"IDN.21.18_1":{"FOI":{"mean":0.023,"sd":0},"serop9":{"mean":43.9793,"sd":0}},"IDN.21.19_1":{"FOI":{"mean":0.0228,"sd":0},"serop9":{"mean":44.3111,"sd":0}},"IDN.21.2_1":{"FOI":{"mean":0.0239,"sd":0},"serop9":{"mean":42.544,"sd":0}},"IDN.21.20_1":{"FOI":{"mean":0.0223,"sd":0},"serop9":{"mean":45.0689,"sd":0}},"IDN.21.21_1":{"FOI":{"mean":0.0235,"sd":0},"serop9":{"mean":43.2505,"sd":0}},"IDN.21.3_1":{"FOI":{"mean":0.0296,"sd":0},"serop9":{"mean":34.5909,"sd":0}},"IDN.21.4_1":{"FOI":{"mean":0.0304,"sd":0},"serop9":{"mean":33.7182,"sd":0}},"IDN.21.5_1":{"FOI":{"mean":0.0258,"sd":0},"serop9":{"mean":39.8606,"sd":0}},"IDN.21.6_1":{"FOI":{"mean":0.0264,"sd":0},"serop9":{"mean":38.9907,"sd":0}},"IDN.21.7_1":{"FOI":{"mean":0.0318,"sd":0},"serop9":{"mean":32.002,"sd":0}},"IDN.21.8_1":{"FOI":{"mean":0.03,"sd":0},"serop9":{"mean":34.1755,"sd":0}},"IDN.21.9_1":{"FOI":{"mean":0.0292,"sd":0},"serop9":{"mean":35.1615,"sd":0}},"IDN.22.1_1":{"FOI":{"mean":0.0236,"sd":0},"serop9":{"mean":42.9565,"sd":0}},"IDN.22.10_1":{"FOI":{"mean":0.0264,"sd":0},"serop9":{"mean":38.8396,"sd":0}},"IDN.22.11_1":{"FOI":{"mean":0.0257,"sd":0},"serop9":{"mean":39.8504,"sd":0}},"IDN.22.2_1":{"FOI":{"mean":0.0246,"sd":0},"serop9":{"mean":41.3888,"sd":0}},"IDN.22.3_1":{"FOI":{"mean":0.0227,"sd":0},"serop9":{"mean":44.5249,"sd":0}},"IDN.22.4_1":{"FOI":{"mean":0.0312,"sd":0},"serop9":{"mean":32.6427,"sd":0}},"IDN.22.5_1":{"FOI":{"mean":0.0218,"sd":0},"serop9":{"mean":45.9784,"sd":0}},"IDN.22.6_1":{"FOI":{"mean":0.0277,"sd":0},"serop9":{"mean":37.0619,"sd":0}},"IDN.22.7_1":{"FOI":{"mean":0.0233,"sd":0},"serop9":{"mean":43.369,"sd":0}},"IDN.22.8_1":{"FOI":{"mean":0.0243,"sd":0},"serop9":{"mean":41.7594,"sd":0}},"IDN.22.9_1":{"FOI":{"mean":0.0239,"sd":0},"serop9":{"mean":42.4516,"sd":0}},"IDN.23.1_1":{"FOI":{"mean":0.0195,"sd":0},"serop9":{"mean":49.7437,"sd":0}},"IDN.23.10_1":{"FOI":{"mean":0.027,"sd":0},"serop9":{"mean":38.0195,"sd":0}},"IDN.23.11_1":{"FOI":{"mean":0.0365,"sd":0},"serop9":{"mean":26.9952,"sd":0}},"IDN.23.12_1":{"FOI":{"mean":0.014,"sd":0},"serop9":{"mean":60.784,"sd":0}},"IDN.23.13_1":{"FOI":{"mean":0.0267,"sd":0},"serop9":{"mean":38.4425,"sd":0}},"IDN.23.14_1":{"FOI":{"mean":0.0191,"sd":0},"serop9":{"mean":50.463,"sd":0}},"IDN.23.15_1":{"FOI":{"mean":0.0212,"sd":0},"serop9":{"mean":46.7048,"sd":0}},"IDN.23.16_1":{"FOI":{"mean":0.0265,"sd":0},"serop9":{"mean":38.7238,"sd":0}},"IDN.23.17_1":{"FOI":{"mean":0.0177,"sd":0},"serop9":{"mean":52.9675,"sd":0}},"IDN.23.18_1":{"FOI":{"mean":0.0248,"sd":0},"serop9":{"mean":41.056,"sd":0}},"IDN.23.19_1":{"FOI":{"mean":0.0134,"sd":0},"serop9":{"mean":62.1071,"sd":0}},"IDN.23.2_1":{"FOI":{"mean":0.032,"sd":0},"serop9":{"mean":31.7575,"sd":0}},"IDN.23.20_1":{"FOI":{"mean":0.0171,"sd":0},"serop9":{"mean":54.3922,"sd":0}},"IDN.23.21_1":{"FOI":{"mean":0.0204,"sd":0},"serop9":{"mean":48.0854,"sd":0}},"IDN.23.22_1":{"FOI":{"mean":0.0182,"sd":0},"serop9":{"mean":52.0755,"sd":0}},"IDN.23.23_1":{"FOI":{"mean":0.0158,"sd":0},"serop9":{"mean":56.9078,"sd":0}},"IDN.23.24_1":{"FOI":{"mean":0.0267,"sd":0},"serop9":{"mean":38.339,"sd":0}},"IDN.23.25_1":{"FOI":{"mean":0.0297,"sd":0},"serop9":{"mean":34.4879,"sd":0}},"IDN.23.26_1":{"FOI":{"mean":0.0167,"sd":0},"serop9":{"mean":54.9759,"sd":0}},"IDN.23.27_1":{"FOI":{"mean":0.0245,"sd":0},"serop9":{"mean":41.5516,"sd":0}},"IDN.23.28_1":{"FOI":{"mean":0.0147,"sd":0},"serop9":{"mean":59.0544,"sd":0}},"IDN.23.29_1":{"FOI":{"mean":0.0258,"sd":0},"serop9":{"mean":39.5679,"sd":0}},"IDN.23.3_1":{"FOI":{"mean":0.0193,"sd":0},"serop9":{"mean":50.0102,"sd":0}},"IDN.23.4_1":{"FOI":{"mean":0.0188,"sd":0},"serop9":{"mean":51.0566,"sd":0}},"IDN.23.5_1":{"FOI":{"mean":0.0208,"sd":0},"serop9":{"mean":47.4955,"sd":0}},"IDN.23.6_1":{"FOI":{"mean":0.0172,"sd":0},"serop9":{"mean":54.0038,"sd":0}},"IDN.23.7_1":{"FOI":{"mean":0.0305,"sd":0},"serop9":{"mean":33.4868,"sd":0}},"IDN.23.8_1":{"FOI":{"mean":0.0151,"sd":0},"serop9":{"mean":58.3932,"sd":0}},"IDN.23.9_1":{"FOI":{"mean":0.0314,"sd":0},"serop9":{"mean":32.4474,"sd":0}},"IDN.24.1_1":{"FOI":{"mean":0.0346,"sd":0},"serop9":{"mean":28.9297,"sd":0}},"IDN.24.10_1":{"FOI":{"mean":0.0339,"sd":0},"serop9":{"mean":29.5998,"sd":0}},"IDN.24.11_1":{"FOI":{"mean":0.0311,"sd":0},"serop9":{"mean":32.8936,"sd":0}},"IDN.24.12_1":{"FOI":{"mean":0.0312,"sd":0},"serop9":{"mean":32.7028,"sd":0}},"IDN.24.2_1":{"FOI":{"mean":0.0361,"sd":0},"serop9":{"mean":27.4302,"sd":0}},"IDN.24.3_1":{"FOI":{"mean":0.0312,"sd":0},"serop9":{"mean":32.7348,"sd":0}},"IDN.24.4_1":{"FOI":{"mean":0.029,"sd":0},"serop9":{"mean":35.5073,"sd":0}},"IDN.24.5_1":{"FOI":{"mean":0.0336,"sd":0},"serop9":{"mean":29.9807,"sd":0}},"IDN.24.6_1":{"FOI":{"mean":0.0305,"sd":0},"serop9":{"mean":33.5127,"sd":0}},"IDN.24.7_1":{"FOI":{"mean":0.029,"sd":0},"serop9":{"mean":35.4599,"sd":0}},"IDN.24.8_1":{"FOI":{"mean":0.0333,"sd":0},"serop9":{"mean":30.4448,"sd":0}},"IDN.24.9_1":{"FOI":{"mean":0.0301,"sd":0},"serop9":{"mean":34.0118,"sd":0}},"IDN.25.1_1":{"FOI":{"mean":0.0277,"sd":0},"serop9":{"mean":37.0585,"sd":0}},"IDN.25.2_1":{"FOI":{"mean":0.0187,"sd":0},"serop9":{"mean":51.1087,"sd":0}},"IDN.25.3_1":{"FOI":{"mean":0.0318,"sd":0},"serop9":{"mean":32.0207,"sd":0}},"IDN.25.4_1":{"FOI":{"mean":0.0301,"sd":0},"serop9":{"mean":34.0214,"sd":0}},"IDN.25.5_1":{"FOI":{"mean":0.0281,"sd":0},"serop9":{"mean":36.564,"sd":0}},"IDN.26.1_1":{"FOI":{"mean":0.0238,"sd":0},"serop9":{"mean":42.752,"sd":0}},"IDN.26.10_1":{"FOI":{"mean":0.0302,"sd":0},"serop9":{"mean":34.1666,"sd":0}},"IDN.26.11_1":{"FOI":{"mean":0.0338,"sd":0},"serop9":{"mean":30.3665,"sd":0}},"IDN.26.12_1":{"FOI":{"mean":0.0285,"sd":0},"serop9":{"mean":36.2163,"sd":0}},"IDN.26.13_1":{"FOI":{"mean":0.0269,"sd":0},"serop9":{"mean":38.2064,"sd":0}},"IDN.26.14_1":{"FOI":{"mean":0.0318,"sd":0},"serop9":{"mean":32.5634,"sd":0}},"IDN.26.15_1":{"FOI":{"mean":0.0297,"sd":0},"serop9":{"mean":34.6927,"sd":0}},"IDN.26.16_1":{"FOI":{"mean":0.0246,"sd":0},"serop9":{"mean":41.4735,"sd":0}},"IDN.26.17_1":{"FOI":{"mean":0.0282,"sd":0},"serop9":{"mean":36.4565,"sd":0}},"IDN.26.18_1":{"FOI":{"mean":0.0268,"sd":0},"serop9":{"mean":38.3239,"sd":0}},"IDN.26.19_1":{"FOI":{"mean":0.0284,"sd":0},"serop9":{"mean":36.4468,"sd":0}},"IDN.26.2_1":{"FOI":{"mean":0.025,"sd":0},"serop9":{"mean":40.9558,"sd":0}},"IDN.26.20_1":{"FOI":{"mean":0.0243,"sd":0},"serop9":{"mean":42.02,"sd":0}},"IDN.26.21_1":{"FOI":{"mean":0.0278,"sd":0},"serop9":{"mean":37.1119,"sd":0}},"IDN.26.22_1":{"FOI":{"mean":0.0277,"sd":0},"serop9":{"mean":37.1802,"sd":0}},"IDN.26.23_1":{"FOI":{"mean":0.0278,"sd":0},"serop9":{"mean":37.0592,"sd":0}},"IDN.26.24_1":{"FOI":{"mean":0.0281,"sd":0},"serop9":{"mean":36.7198,"sd":0}},"IDN.26.3_1":{"FOI":{"mean":0.026,"sd":0},"serop9":{"mean":39.5145,"sd":0}},"IDN.26.4_1":{"FOI":{"mean":0.0254,"sd":0},"serop9":{"mean":40.3207,"sd":0}},"IDN.26.5_1":{"FOI":{"mean":0.0257,"sd":0},"serop9":{"mean":39.8419,"sd":0}},"IDN.26.6_1":{"FOI":{"mean":0.0241,"sd":0},"serop9":{"mean":42.3206,"sd":0}},"IDN.26.7_1":{"FOI":{"mean":0.0275,"sd":0},"serop9":{"mean":37.3656,"sd":0}},"IDN.26.8_1":{"FOI":{"mean":0.0289,"sd":0},"serop9":{"mean":35.5797,"sd":0}},"IDN.26.9_1":{"FOI":{"mean":0.0375,"sd":0},"serop9":{"mean":27.0014,"sd":0}},"IDN.27.1_1":{"FOI":{"mean":0.028,"sd":0},"serop9":{"mean":36.648,"sd":0}},"IDN.27.10_1":{"FOI":{"mean":0.026,"sd":0},"serop9":{"mean":39.3724,"sd":0}},"IDN.27.11_1":{"FOI":{"mean":0.032,"sd":0},"serop9":{"mean":31.7329,"sd":0}},"IDN.27.2_1":{"FOI":{"mean":0.0308,"sd":0},"serop9":{"mean":33.1975,"sd":0}},"IDN.27.3_1":{"FOI":{"mean":0.0316,"sd":0},"serop9":{"mean":32.2666,"sd":0}},"IDN.27.4_1":{"FOI":{"mean":0.0323,"sd":0},"serop9":{"mean":31.3222,"sd":0}},"IDN.27.5_1":{"FOI":{"mean":0.0328,"sd":0},"serop9":{"mean":31.3788,"sd":0}},"IDN.27.6_1":{"FOI":{"mean":0.0269,"sd":0},"serop9":{"mean":38.1148,"sd":0}},"IDN.27.7_1":{"FOI":{"mean":0.0285,"sd":0},"serop9":{"mean":36.034,"sd":0}},"IDN.27.8_1":{"FOI":{"mean":0.0273,"sd":0},"serop9":{"mean":37.5733,"sd":0}},"IDN.27.9_1":{"FOI":{"mean":0.0329,"sd":0},"serop9":{"mean":30.7544,"sd":0}},"IDN.28.1_1":{"FOI":{"mean":0.029,"sd":0},"serop9":{"mean":35.5217,"sd":0}},"IDN.28.10_1":{"FOI":{"mean":0.0389,"sd":0},"serop9":{"mean":25.4358,"sd":0}},"IDN.28.11_1":{"FOI":{"mean":0.0319,"sd":0},"serop9":{"mean":32.1362,"sd":0}},"IDN.28.12_1":{"FOI":{"mean":0.0283,"sd":0},"serop9":{"mean":36.2696,"sd":0}},"IDN.28.2_1":{"FOI":{"mean":0.0298,"sd":0},"serop9":{"mean":34.413,"sd":0}},"IDN.28.3_1":{"FOI":{"mean":0.0296,"sd":0},"serop9":{"mean":35.3415,"sd":0}},"IDN.28.4_1":{"FOI":{"mean":0.0283,"sd":0},"serop9":{"mean":36.2696,"sd":0}},"IDN.28.5_1":{"FOI":{"mean":0.066,"sd":0},"serop9":{"mean":13.9109,"sd":0}},"IDN.28.6_1":{"FOI":{"mean":0.0248,"sd":0},"serop9":{"mean":41.2182,"sd":0}},"IDN.28.7_1":{"FOI":{"mean":0.0312,"sd":0},"serop9":{"mean":32.8008,"sd":0}},"IDN.28.8_1":{"FOI":{"mean":0.0399,"sd":0},"serop9":{"mean":24.7138,"sd":0}},"IDN.28.9_1":{"FOI":{"mean":0.037,"sd":0},"serop9":{"mean":27.5252,"sd":0}},"IDN.29.1_1":{"FOI":{"mean":0.0259,"sd":0},"serop9":{"mean":39.5858,"sd":0}},"IDN.29.10_1":{"FOI":{"mean":0.0318,"sd":0},"serop9":{"mean":32.011,"sd":0}},"IDN.29.11_1":{"FOI":{"mean":0.0293,"sd":0},"serop9":{"mean":34.9809,"sd":0}},"IDN.29.12_1":{"FOI":{"mean":0.0327,"sd":0},"serop9":{"mean":31.001,"sd":0}},"IDN.29.13_1":{"FOI":{"mean":0.0298,"sd":0},"serop9":{"mean":34.2808,"sd":0}},"IDN.29.14_1":{"FOI":{"mean":0.0386,"sd":0},"serop9":{"mean":25.0279,"sd":0}},"IDN.29.15_1":{"FOI":{"mean":0.036,"sd":0},"serop9":{"mean":27.5391,"sd":0}},"IDN.29.2_1":{"FOI":{"mean":0.0284,"sd":0},"serop9":{"mean":36.1342,"sd":0}},"IDN.29.3_1":{"FOI":{"mean":0.0289,"sd":0},"serop9":{"mean":35.4389,"sd":0}},"IDN.29.4_1":{"FOI":{"mean":0.0314,"sd":0},"serop9":{"mean":32.491,"sd":0}},"IDN.29.5_1":{"FOI":{"mean":0.0301,"sd":0},"serop9":{"mean":33.9423,"sd":0}},"IDN.29.6_1":{"FOI":{"mean":0.0386,"sd":0},"serop9":{"mean":25.0279,"sd":0}},"IDN.29.7_1":{"FOI":{"mean":0.0324,"sd":0},"serop9":{"mean":31.3167,"sd":0}},"IDN.29.8_1":{"FOI":{"mean":0.0289,"sd":0},"serop9":{"mean":35.4389,"sd":0}},"IDN.29.9_1":{"FOI":{"mean":0.0327,"sd":0},"serop9":{"mean":31.001,"sd":0}},"IDN.3.1_1":{"FOI":{"mean":0.0293,"sd":0},"serop9":{"mean":35.0617,"sd":0}},"IDN.3.2_1":{"FOI":{"mean":0.0295,"sd":0},"serop9":{"mean":34.7975,"sd":0}},"IDN.3.3_1":{"FOI":{"mean":0.0295,"sd":0},"serop9":{"mean":34.779,"sd":0}},"IDN.3.4_1":{"FOI":{"mean":0.0306,"sd":0},"serop9":{"mean":33.4717,"sd":0}},"IDN.3.5_1":{"FOI":{"mean":0.0293,"sd":0},"serop9":{"mean":35.0177,"sd":0}},"IDN.3.6_1":{"FOI":{"mean":0.0288,"sd":0},"serop9":{"mean":35.7125,"sd":0}},"IDN.3.7_1":{"FOI":{"mean":0.0306,"sd":0},"serop9":{"mean":33.4717,"sd":0}},"IDN.30.1_1":{"FOI":{"mean":0.0307,"sd":0},"serop9":{"mean":33.2795,"sd":0}},"IDN.30.10_1":{"FOI":{"mean":0.0321,"sd":0},"serop9":{"mean":31.6535,"sd":0}},"IDN.30.11_1":{"FOI":{"mean":0.0302,"sd":0},"serop9":{"mean":33.8905,"sd":0}},"IDN.30.12_1":{"FOI":{"mean":0.0302,"sd":0},"serop9":{"mean":33.8336,"sd":0}},"IDN.30.13_1":{"FOI":{"mean":0.0301,"sd":0},"serop9":{"mean":33.9888,"sd":0}},"IDN.30.14_1":{"FOI":{"mean":0.0306,"sd":0},"serop9":{"mean":33.4019,"sd":0}},"IDN.30.15_1":{"FOI":{"mean":0.0258,"sd":0},"serop9":{"mean":39.677,"sd":0}},"IDN.30.16_1":{"FOI":{"mean":0.0306,"sd":0},"serop9":{"mean":33.4019,"sd":0}},"IDN.30.17_1":{"FOI":{"mean":0.0286,"sd":0},"serop9":{"mean":36.057,"sd":0}},"IDN.30.18_1":{"FOI":{"mean":0.0265,"sd":0},"serop9":{"mean":38.865,"sd":0}},"IDN.30.19_1":{"FOI":{"mean":0.03,"sd":0},"serop9":{"mean":34.123,"sd":0}},"IDN.30.2_1":{"FOI":{"mean":0.0307,"sd":0},"serop9":{"mean":33.2795,"sd":0}},"IDN.30.20_1":{"FOI":{"mean":0.0306,"sd":0},"serop9":{"mean":33.4019,"sd":0}},"IDN.30.3_1":{"FOI":{"mean":0.0306,"sd":0},"serop9":{"mean":33.4019,"sd":0}},"IDN.30.4_1":{"FOI":{"mean":0.0304,"sd":0},"serop9":{"mean":33.9085,"sd":0}},"IDN.30.5_1":{"FOI":{"mean":0.0272,"sd":0},"serop9":{"mean":37.6646,"sd":0}},"IDN.30.6_1":{"FOI":{"mean":0.0321,"sd":0},"serop9":{"mean":31.6535,"sd":0}},"IDN.30.7_1":{"FOI":{"mean":0.0296,"sd":0},"serop9":{"mean":34.668,"sd":0}},"IDN.30.8_1":{"FOI":{"mean":0.0306,"sd":0},"serop9":{"mean":33.4019,"sd":0}},"IDN.30.9_1":{"FOI":{"mean":0.0302,"sd":0},"serop9":{"mean":33.8905,"sd":0}},"IDN.31.1_1":{"FOI":{"mean":0.0305,"sd":0},"serop9":{"mean":33.5158,"sd":0}},"IDN.31.10_1":{"FOI":{"mean":0.0319,"sd":0},"serop9":{"mean":32.0131,"sd":0}},"IDN.31.11_1":{"FOI":{"mean":0.0392,"sd":0},"serop9":{"mean":24.8139,"sd":0}},"IDN.31.12_1":{"FOI":{"mean":0.0349,"sd":0},"serop9":{"mean":28.8676,"sd":0}},"IDN.31.13_1":{"FOI":{"mean":0.0268,"sd":0},"serop9":{"mean":38.454,"sd":0}},"IDN.31.14_1":{"FOI":{"mean":0.0316,"sd":0},"serop9":{"mean":32.2663,"sd":0}},"IDN.31.15_1":{"FOI":{"mean":0.035,"sd":0},"serop9":{"mean":28.9478,"sd":0}},"IDN.31.2_1":{"FOI":{"mean":0.0321,"sd":0},"serop9":{"mean":31.8339,"sd":0}},"IDN.31.3_1":{"FOI":{"mean":0.0335,"sd":0},"serop9":{"mean":30.2832,"sd":0}},"IDN.31.4_1":{"FOI":{"mean":0.0326,"sd":0},"serop9":{"mean":31.3262,"sd":0}},"IDN.31.5_1":{"FOI":{"mean":0.0324,"sd":0},"serop9":{"mean":31.5617,"sd":0}},"IDN.31.6_1":{"FOI":{"mean":0.0297,"sd":0},"serop9":{"mean":34.6512,"sd":0}},"IDN.31.7_1":{"FOI":{"mean":0.03,"sd":0},"serop9":{"mean":34.3646,"sd":0}},"IDN.31.8_1":{"FOI":{"mean":0.0315,"sd":0},"serop9":{"mean":32.4134,"sd":0}},"IDN.31.9_1":{"FOI":{"mean":0.0328,"sd":0},"serop9":{"mean":30.9216,"sd":0}},"IDN.32.1_1":{"FOI":{"mean":0.0351,"sd":0},"serop9":{"mean":28.3568,"sd":0}},"IDN.32.10_1":{"FOI":{"mean":0.0351,"sd":0},"serop9":{"mean":28.3568,"sd":0}},"IDN.32.11_1":{"FOI":{"mean":0.034,"sd":0},"serop9":{"mean":29.471,"sd":0}},"IDN.32.12_1":{"FOI":{"mean":0.0356,"sd":0},"serop9":{"mean":27.8793,"sd":0}},"IDN.32.13_1":{"FOI":{"mean":0.035,"sd":0},"serop9":{"mean":28.4476,"sd":0}},"IDN.32.14_1":{"FOI":{"mean":0.0291,"sd":0},"serop9":{"mean":35.4156,"sd":0}},"IDN.32.15_1":{"FOI":{"mean":0.0355,"sd":0},"serop9":{"mean":27.9918,"sd":0}},"IDN.32.16_1":{"FOI":{"mean":0.0278,"sd":0},"serop9":{"mean":36.9307,"sd":0}},"IDN.32.17_1":{"FOI":{"mean":0.0347,"sd":0},"serop9":{"mean":28.7667,"sd":0}},"IDN.32.18_1":{"FOI":{"mean":0.0339,"sd":0},"serop9":{"mean":29.6168,"sd":0}},"IDN.32.19_1":{"FOI":{"mean":0.0323,"sd":0},"serop9":{"mean":31.4246,"sd":0}},"IDN.32.2_1":{"FOI":{"mean":0.0355,"sd":0},"serop9":{"mean":27.9651,"sd":0}},"IDN.32.20_1":{"FOI":{"mean":0.0326,"sd":0},"serop9":{"mean":31.03,"sd":0}},"IDN.32.21_1":{"FOI":{"mean":0.0336,"sd":0},"serop9":{"mean":29.9991,"sd":0}},"IDN.32.22_1":{"FOI":{"mean":0.0326,"sd":0},"serop9":{"mean":31.0918,"sd":0}},"IDN.32.23_1":{"FOI":{"mean":0.0336,"sd":0},"serop9":{"mean":30.1084,"sd":0}},"IDN.32.24_1":{"FOI":{"mean":0.0299,"sd":0},"serop9":{"mean":34.275,"sd":0}},"IDN.32.25_1":{"FOI":{"mean":0.0347,"sd":0},"serop9":{"mean":28.8372,"sd":0}},"IDN.32.26_1":{"FOI":{"mean":0.031,"sd":0},"serop9":{"mean":33.3132,"sd":0}},"IDN.32.27_1":{"FOI":{"mean":0.0357,"sd":0},"serop9":{"mean":27.8244,"sd":0}},"IDN.32.28_1":{"FOI":{"mean":0.0309,"sd":0},"serop9":{"mean":32.9208,"sd":0}},"IDN.32.29_1":{"FOI":{"mean":0.0347,"sd":0},"serop9":{"mean":28.8372,"sd":0}},"IDN.32.3_1":{"FOI":{"mean":0.0315,"sd":0},"serop9":{"mean":32.3953,"sd":0}},"IDN.32.30_1":{"FOI":{"mean":0.0324,"sd":0},"serop9":{"mean":31.2642,"sd":0}},"IDN.32.31_1":{"FOI":{"mean":0.0309,"sd":0},"serop9":{"mean":32.9208,"sd":0}},"IDN.32.32_1":{"FOI":{"mean":0.0286,"sd":0},"serop9":{"mean":36.0021,"sd":0}},"IDN.32.33_1":{"FOI":{"mean":0.0364,"sd":0},"serop9":{"mean":27.1365,"sd":0}},"IDN.32.34_1":{"FOI":{"mean":0.0283,"sd":0},"serop9":{"mean":36.3926,"sd":0}},"IDN.32.4_1":{"FOI":{"mean":0.0401,"sd":0},"serop9":{"mean":23.7861,"sd":0}},"IDN.32.5_1":{"FOI":{"mean":0.0286,"sd":0},"serop9":{"mean":35.8483,"sd":0}},"IDN.32.6_1":{"FOI":{"mean":0.0275,"sd":0},"serop9":{"mean":37.4571,"sd":0}},"IDN.32.7_1":{"FOI":{"mean":0.0322,"sd":0},"serop9":{"mean":31.7865,"sd":0}},"IDN.32.8_1":{"FOI":{"mean":0.0364,"sd":0},"serop9":{"mean":27.1326,"sd":0}},"IDN.32.9_1":{"FOI":{"mean":0.0414,"sd":0},"serop9":{"mean":23.2092,"sd":0}},"IDN.33.1_1":{"FOI":{"mean":0.0328,"sd":0},"serop9":{"mean":30.9761,"sd":0}},"IDN.33.2_1":{"FOI":{"mean":0.0321,"sd":0},"serop9":{"mean":31.7034,"sd":0}},"IDN.33.3_1":{"FOI":{"mean":0.0283,"sd":0},"serop9":{"mean":36.4163,"sd":0}},"IDN.33.4_1":{"FOI":{"mean":0.0305,"sd":0},"serop9":{"mean":33.4597,"sd":0}},"IDN.33.5_1":{"FOI":{"mean":0.0283,"sd":0},"serop9":{"mean":36.4163,"sd":0}},"IDN.34.1_1":{"FOI":{"mean":0.0326,"sd":0},"serop9":{"mean":30.9761,"sd":0}},"IDN.34.10_1":{"FOI":{"mean":0.0305,"sd":0},"serop9":{"mean":33.5115,"sd":0}},"IDN.34.11_1":{"FOI":{"mean":0.0354,"sd":0},"serop9":{"mean":28.0389,"sd":0}},"IDN.34.12_1":{"FOI":{"mean":0.0321,"sd":0},"serop9":{"mean":31.6569,"sd":0}},"IDN.34.2_1":{"FOI":{"mean":0.0323,"sd":0},"serop9":{"mean":31.405,"sd":0}},"IDN.34.3_1":{"FOI":{"mean":0.0321,"sd":0},"serop9":{"mean":31.6569,"sd":0}},"IDN.34.5_1":{"FOI":{"mean":0.026,"sd":0},"serop9":{"mean":39.3679,"sd":0}},"IDN.34.6_1":{"FOI":{"mean":0.0334,"sd":0},"serop9":{"mean":30.1009,"sd":0}},"IDN.34.7_1":{"FOI":{"mean":0.0304,"sd":0},"serop9":{"mean":33.6248,"sd":0}},"IDN.35.13":{"FOI":{"mean":0.0273,"sd":0},"serop9":{"mean":37.5904,"sd":0}},"IDN.35.14":{"FOI":{"mean":0.0273,"sd":0},"serop9":{"mean":37.5904,"sd":0}},"IDN.35.4":{"FOI":{"mean":0.0303,"sd":0},"serop9":{"mean":33.7123,"sd":0}},"IDN.35.8":{"FOI":{"mean":0.026,"sd":0},"serop9":{"mean":39.3122,"sd":0}},"IDN.35.9":{"FOI":{"mean":0.0293,"sd":0},"serop9":{"mean":34.9902,"sd":0}},"IDN.4.1_1":{"FOI":{"mean":0.0393,"sd":0},"serop9":{"mean":24.4397,"sd":0}},"IDN.4.2_1":{"FOI":{"mean":0.0333,"sd":0},"serop9":{"mean":30.2755,"sd":0}},"IDN.4.3_1":{"FOI":{"mean":0.0457,"sd":0},"serop9":{"mean":19.471,"sd":0}},"IDN.4.4_1":{"FOI":{"mean":0.0328,"sd":0},"serop9":{"mean":30.8973,"sd":0}},"IDN.4.5_1":{"FOI":{"mean":0.0311,"sd":0},"serop9":{"mean":32.8065,"sd":0}},"IDN.4.6_1":{"FOI":{"mean":0.0351,"sd":0},"serop9":{"mean":28.3529,"sd":0}},"IDN.4.7_1":{"FOI":{"mean":0.0403,"sd":0},"serop9":{"mean":23.5921,"sd":0}},"IDN.4.8_1":{"FOI":{"mean":0.0393,"sd":0},"serop9":{"mean":24.4175,"sd":0}},"IDN.5.1_1":{"FOI":{"mean":0.0278,"sd":0},"serop9":{"mean":36.8734,"sd":0}},"IDN.5.10_1":{"FOI":{"mean":0.0302,"sd":0},"serop9":{"mean":33.9441,"sd":0}},"IDN.5.2_1":{"FOI":{"mean":0.0299,"sd":0},"serop9":{"mean":34.288,"sd":0}},"IDN.5.3_1":{"FOI":{"mean":0.0288,"sd":0},"serop9":{"mean":35.6945,"sd":0}},"IDN.5.4_1":{"FOI":{"mean":0.0315,"sd":0},"serop9":{"mean":32.3601,"sd":0}},"IDN.5.5_1":{"FOI":{"mean":0.0282,"sd":0},"serop9":{"mean":36.4076,"sd":0}},"IDN.5.6_1":{"FOI":{"mean":0.0268,"sd":0},"serop9":{"mean":38.3605,"sd":0}},"IDN.5.7_1":{"FOI":{"mean":0.0276,"sd":0},"serop9":{"mean":37.1569,"sd":0}},"IDN.5.8_1":{"FOI":{"mean":0.0275,"sd":0},"serop9":{"mean":37.3101,"sd":0}},"IDN.5.9_1":{"FOI":{"mean":0.0296,"sd":0},"serop9":{"mean":34.7737,"sd":0}},"IDN.6.1_1":{"FOI":{"mean":0.0266,"sd":0},"serop9":{"mean":38.5852,"sd":0}},"IDN.6.2_1":{"FOI":{"mean":0.0257,"sd":0},"serop9":{"mean":39.8311,"sd":0}},"IDN.6.3_1":{"FOI":{"mean":0.0323,"sd":0},"serop9":{"mean":31.3853,"sd":0}},"IDN.6.4_1":{"FOI":{"mean":0.0326,"sd":0},"serop9":{"mean":31.1017,"sd":0}},"IDN.6.5_1":{"FOI":{"mean":0.0323,"sd":0},"serop9":{"mean":31.3853,"sd":0}},"IDN.6.6_1":{"FOI":{"mean":0.0257,"sd":0},"serop9":{"mean":39.8311,"sd":0}},"IDN.6.7_1":{"FOI":{"mean":0.0268,"sd":0},"serop9":{"mean":38.254,"sd":0}},"IDN.7.1_1":{"FOI":{"mean":0.0384,"sd":0},"serop9":{"mean":25.2047,"sd":0}},"IDN.7.2_1":{"FOI":{"mean":0.0384,"sd":0},"serop9":{"mean":25.2047,"sd":0}},"IDN.7.3_1":{"FOI":{"mean":0.0423,"sd":0},"serop9":{"mean":21.9755,"sd":0}},"IDN.7.4_1":{"FOI":{"mean":0.042,"sd":0},"serop9":{"mean":22.2654,"sd":0}},"IDN.7.5_1":{"FOI":{"mean":0.0384,"sd":0},"serop9":{"mean":25.2047,"sd":0}},"IDN.8.1_1":{"FOI":{"mean":0.029,"sd":0},"serop9":{"mean":35.4556,"sd":0}},"IDN.8.10_1":{"FOI":{"mean":0.0296,"sd":0},"serop9":{"mean":34.6382,"sd":0}},"IDN.8.11_1":{"FOI":{"mean":0.0294,"sd":0},"serop9":{"mean":35.0675,"sd":0}},"IDN.8.2_1":{"FOI":{"mean":0.0363,"sd":0},"serop9":{"mean":28.1159,"sd":0}},"IDN.8.3_1":{"FOI":{"mean":0.0319,"sd":0},"serop9":{"mean":31.8955,"sd":0}},"IDN.8.4_1":{"FOI":{"mean":0.0228,"sd":0},"serop9":{"mean":44.2368,"sd":0}},"IDN.8.5_1":{"FOI":{"mean":0.0293,"sd":0},"serop9":{"mean":35.2979,"sd":0}},"IDN.8.6_1":{"FOI":{"mean":0.0319,"sd":0},"serop9":{"mean":31.8955,"sd":0}},"IDN.8.7_1":{"FOI":{"mean":0.0294,"sd":0},"serop9":{"mean":35.1141,"sd":0}},"IDN.8.8_1":{"FOI":{"mean":0.0287,"sd":0},"serop9":{"mean":35.9435,"sd":0}},"IDN.8.9_1":{"FOI":{"mean":0.0294,"sd":0},"serop9":{"mean":34.936,"sd":0}},"IDN.9.1_1":{"FOI":{"mean":0.0321,"sd":0},"serop9":{"mean":31.7039,"sd":0}},"IDN.9.10_1":{"FOI":{"mean":0.0423,"sd":0},"serop9":{"mean":21.9755,"sd":0}},"IDN.9.11_1":{"FOI":{"mean":0.0306,"sd":0},"serop9":{"mean":33.5706,"sd":0}},"IDN.9.12_1":{"FOI":{"mean":0.0364,"sd":0},"serop9":{"mean":27.479,"sd":0}},"IDN.9.13_1":{"FOI":{"mean":0.0424,"sd":0},"serop9":{"mean":21.8712,"sd":0}},"IDN.9.14_1":{"FOI":{"mean":0.0371,"sd":0},"serop9":{"mean":26.7247,"sd":0}},"IDN.9.15_1":{"FOI":{"mean":0.042,"sd":0},"serop9":{"mean":22.2654,"sd":0}},"IDN.9.16_1":{"FOI":{"mean":0.0384,"sd":0},"serop9":{"mean":25.3862,"sd":0}},"IDN.9.17_1":{"FOI":{"mean":0.0516,"sd":0},"serop9":{"mean":16.1251,"sd":0}},"IDN.9.18_1":{"FOI":{"mean":0.0309,"sd":0},"serop9":{"mean":33.0832,"sd":0}},"IDN.9.19_1":{"FOI":{"mean":0.0298,"sd":0},"serop9":{"mean":34.3684,"sd":0}},"IDN.9.2_1":{"FOI":{"mean":0.0371,"sd":0},"serop9":{"mean":26.7247,"sd":0}},"IDN.9.20_1":{"FOI":{"mean":0.0476,"sd":0},"serop9":{"mean":18.65,"sd":0}},"IDN.9.21_1":{"FOI":{"mean":0.0387,"sd":0},"serop9":{"mean":25.2955,"sd":0}},"IDN.9.22_1":{"FOI":{"mean":0.0415,"sd":0},"serop9":{"mean":22.7479,"sd":0}},"IDN.9.23_1":{"FOI":{"mean":0.0405,"sd":0},"serop9":{"mean":23.4744,"sd":0}},"IDN.9.24_1":{"FOI":{"mean":0.0309,"sd":0},"serop9":{"mean":33.0832,"sd":0}},"IDN.9.25_1":{"FOI":{"mean":0.0393,"sd":0},"serop9":{"mean":24.9112,"sd":0}},"IDN.9.26_1":{"FOI":{"mean":0.0275,"sd":0},"serop9":{"mean":37.3047,"sd":0}},"IDN.9.27_1":{"FOI":{"mean":0.0415,"sd":0},"serop9":{"mean":22.7479,"sd":0}},"IDN.9.3_1":{"FOI":{"mean":0.0299,"sd":0},"serop9":{"mean":34.2375,"sd":0}},"IDN.9.4_1":{"FOI":{"mean":0.0406,"sd":0},"serop9":{"mean":23.3623,"sd":0}},"IDN.9.5_1":{"FOI":{"mean":0.0397,"sd":0},"serop9":{"mean":24.1073,"sd":0}},"IDN.9.6_1":{"FOI":{"mean":0.0299,"sd":0},"serop9":{"mean":34.2375,"sd":0}},"IDN.9.7_1":{"FOI":{"mean":0.0316,"sd":0},"serop9":{"mean":32.2817,"sd":0}},"IDN.9.8_1":{"FOI":{"mean":0.0321,"sd":0},"serop9":{"mean":31.7039,"sd":0}},"IDN.9.9_1":{"FOI":{"mean":0.0516,"sd":0},"serop9":{"mean":16.1251,"sd":0}},"TLS.6.2_1":{"FOI":{"mean":0.0239,"sd":0},"serop9":{"mean":42.544,"sd":0}}}
