{"type":"FeatureCollection", "features": [
{"type":"Feature","geometry":{"type":"Polygon","coordinates":[[[-61.0361,14.6051],[-61.0375,14.6446],[-61.0807,14.702],[-61.0873,14.7081],[-61.1025,14.7042],[-61.0913,14.6519],[-61.0909,14.5988],[-61.0361,14.6051]]]},"properties":{"GID_0":"MTQ","COUNTRY":"Martinique","GID_1":"MTQ.1_1","NAME_1":"Fort-de-France","NL_NAME_1":"NA","GID_2":"MTQ.1.1_1","NAME_2":"Fort-de-France","VARNAME_2":"NA","NL_NAME_2":"NA","TYPE_2":"Commune","ENGTYPE_2":"Commune","CC_2":"NA","HASC_2":"MQ.FF.FF"}},
{"type":"Feature","geometry":{"type":"Polygon","coordinates":[[[-61.0361,14.6051],[-61.0018,14.5596],[-60.9534,14.6208],[-60.949,14.6315],[-60.9518,14.6448],[-60.9817,14.6915],[-60.9965,14.6755],[-60.9968,14.6613],[-61.0375,14.6446],[-61.0361,14.6051]]]},"properties":{"GID_0":"MTQ","COUNTRY":"Martinique","GID_1":"MTQ.1_1","NAME_1":"Fort-de-France","NL_NAME_1":"NA","GID_2":"MTQ.1.2_1","NAME_2":"LeLamentin","VARNAME_2":"NA","NL_NAME_2":"NA","TYPE_2":"Commune","ENGTYPE_2":"Commune","CC_2":"NA","HASC_2":"MQ.FF.LA"}},
{"type":"Feature","geometry":{"type":"Polygon","coordinates":[[[-61.0375,14.6446],[-60.9968,14.6613],[-61.016,14.6834],[-61.0864,14.7211],[-61.0873,14.7081],[-61.0807,14.702],[-61.0375,14.6446]]]},"properties":{"GID_0":"MTQ","COUNTRY":"Martinique","GID_1":"MTQ.1_1","NAME_1":"Fort-de-France","NL_NAME_1":"NA","GID_2":"MTQ.1.3_1","NAME_2":"Saint-Joseph","VARNAME_2":"NA","NL_NAME_2":"NA","TYPE_2":"Commune","ENGTYPE_2":"Commune","CC_2":"NA","HASC_2":"MQ.FF.SJ"}},
{"type":"Feature","geometry":{"type":"Polygon","coordinates":[[[-61.0913,14.6519],[-61.1025,14.7042],[-61.1102,14.7046],[-61.1188,14.6918],[-61.1095,14.6833],[-61.1116,14.6602],[-61.1249,14.6305],[-61.0909,14.5988],[-61.0913,14.6519]]]},"properties":{"GID_0":"MTQ","COUNTRY":"Martinique","GID_1":"MTQ.1_1","NAME_1":"Fort-de-France","NL_NAME_1":"NA","GID_2":"MTQ.1.4_1","NAME_2":"Schœlcher","VARNAME_2":"NA","NL_NAME_2":"NA","TYPE_2":"Commune","ENGTYPE_2":"Commune","CC_2":"NA","HASC_2":"MQ.FF.SC"}},
{"type":"Feature","geometry":{"type":"Polygon","coordinates":[[[-61.0018,14.5596],[-60.9949,14.5518],[-60.957,14.5495],[-60.9478,14.5593],[-60.9332,14.5862],[-61.0018,14.5596]]]},"properties":{"GID_0":"MTQ","COUNTRY":"Martinique","GID_1":"MTQ.2_1","NAME_1":"LeMarin","NL_NAME_1":"NA","GID_2":"MTQ.2.1_1","NAME_2":"Ducos","VARNAME_2":"NA","NL_NAME_2":"NA","TYPE_2":"Commune","ENGTYPE_2":"Commune","CC_2":"NA","HASC_2":"MQ.MA.DU"}},
{"type":"Feature","geometry":{"type":"Polygon","coordinates":[[[-61.0559,14.4637],[-60.9823,14.4807],[-60.985,14.4991],[-61.0106,14.5086],[-61.0439,14.4998],[-61.0559,14.4637]]]},"properties":{"GID_0":"MTQ","COUNTRY":"Martinique","GID_1":"MTQ.2_1","NAME_1":"LeMarin","NL_NAME_1":"NA","GID_2":"MTQ.2.2_1","NAME_2":"LeDiamant","VARNAME_2":"NA","NL_NAME_2":"NA","TYPE_2":"Commune","ENGTYPE_2":"Commune","CC_2":"NA","HASC_2":"MQ.MA.DI"}},
{"type":"Feature","geometry":{"type":"Polygon","coordinates":[[[-60.9534,14.6208],[-60.9219,14.5761],[-60.9102,14.5805],[-60.8949,14.5588],[-60.8719,14.5817],[-60.8605,14.5899],[-60.9033,14.6485],[-60.9359,14.6283],[-60.949,14.6315],[-60.9534,14.6208]]]},"properties":{"GID_0":"MTQ","COUNTRY":"Martinique","GID_1":"MTQ.2_1","NAME_1":"LeMarin","NL_NAME_1":"NA","GID_2":"MTQ.2.3_1","NAME_2":"LeFrançois","VARNAME_2":"NA","NL_NAME_2":"NA","TYPE_2":"Commune","ENGTYPE_2":"Commune","CC_2":"NA","HASC_2":"MQ.MA.FR"}},
{"type":"Feature","geometry":{"type":"Polygon","coordinates":[[[-60.904,14.4537],[-60.8434,14.4734],[-60.8182,14.4683],[-60.8237,14.4982],[-60.8681,14.5088],[-60.8675,14.5002],[-60.8773,14.4886],[-60.904,14.4537]]]},"properties":{"GID_0":"MTQ","COUNTRY":"Martinique","GID_1":"MTQ.2_1","NAME_1":"LeMarin","NL_NAME_1":"NA","GID_2":"MTQ.2.4_1","NAME_2":"LeMarin","VARNAME_2":"NA","NL_NAME_2":"NA","TYPE_2":"Commune","ENGTYPE_2":"Commune","CC_2":"NA","HASC_2":"MQ.MA.MN"}},
{"type":"Feature","geometry":{"type":"Polygon","coordinates":[[[-60.8949,14.5588],[-60.8954,14.5411],[-60.8697,14.5293],[-60.8681,14.5088],[-60.8237,14.4982],[-60.8605,14.5899],[-60.8719,14.5817],[-60.8949,14.5588]]]},"properties":{"GID_0":"MTQ","COUNTRY":"Martinique","GID_1":"MTQ.2_1","NAME_1":"LeMarin","NL_NAME_1":"NA","GID_2":"MTQ.2.5_1","NAME_2":"LeVauclin","VARNAME_2":"NA","NL_NAME_2":"NA","TYPE_2":"Commune","ENGTYPE_2":"Commune","CC_2":"NA","HASC_2":"MQ.MA.VA"}},
{"type":"Feature","geometry":{"type":"Polygon","coordinates":[[[-61.0439,14.4998],[-61.0546,14.5042],[-61.0692,14.5404],[-61.0559,14.4637],[-61.0439,14.4998]]]},"properties":{"GID_0":"MTQ","COUNTRY":"Martinique","GID_1":"MTQ.2_1","NAME_1":"LeMarin","NL_NAME_1":"NA","GID_2":"MTQ.2.6_1","NAME_2":"LesAnses-d'Arlets","VARNAME_2":"NA","NL_NAME_2":"NA","TYPE_2":"Commune","ENGTYPE_2":"Commune","CC_2":"NA","HASC_2":"MQ.MA.AA"}},
{"type":"Feature","geometry":{"type":"Polygon","coordinates":[[[-61.0546,14.5042],[-61.0009,14.5398],[-61.0015,14.5435],[-61.0692,14.5404],[-61.0546,14.5042]]]},"properties":{"GID_0":"MTQ","COUNTRY":"Martinique","GID_1":"MTQ.2_1","NAME_1":"LeMarin","NL_NAME_1":"NA","GID_2":"MTQ.2.7_1","NAME_2":"LesTrois-Îlets","VARNAME_2":"NA","NL_NAME_2":"NA","TYPE_2":"Commune","ENGTYPE_2":"Commune","CC_2":"NA","HASC_2":"MQ.MA.TI"}},
{"type":"Feature","geometry":{"type":"Polygon","coordinates":[[[-60.8681,14.5088],[-60.8697,14.5293],[-60.8954,14.5411],[-60.9265,14.5354],[-60.9252,14.5206],[-60.9318,14.4993],[-60.9166,14.4685],[-60.904,14.4537],[-60.8773,14.4886],[-60.8675,14.5002],[-60.8681,14.5088]]]},"properties":{"GID_0":"MTQ","COUNTRY":"Martinique","GID_1":"MTQ.2_1","NAME_1":"LeMarin","NL_NAME_1":"NA","GID_2":"MTQ.2.8_1","NAME_2":"Rivière-Pilote","VARNAME_2":"NA","NL_NAME_2":"NA","TYPE_2":"Commune","ENGTYPE_2":"Commune","CC_2":"NA","HASC_2":"MQ.MA.RP"}},
{"type":"Feature","geometry":{"type":"Polygon","coordinates":[[[-60.9949,14.5518],[-61.0015,14.5435],[-61.0009,14.5398],[-61.0106,14.5086],[-60.9252,14.5206],[-60.9265,14.5354],[-60.9562,14.5509],[-60.957,14.5495],[-60.9949,14.5518]]]},"properties":{"GID_0":"MTQ","COUNTRY":"Martinique","GID_1":"MTQ.2_1","NAME_1":"LeMarin","NL_NAME_1":"NA","GID_2":"MTQ.2.9_1","NAME_2":"Rivière-Salée","VARNAME_2":"NA","NL_NAME_2":"NA","TYPE_2":"Commune","ENGTYPE_2":"Commune","CC_2":"NA","HASC_2":"MQ.MA.RS"}},
{"type":"Feature","geometry":{"type":"Polygon","coordinates":[[[-60.9562,14.5509],[-60.8954,14.5411],[-60.9102,14.5805],[-60.9219,14.5761],[-60.9332,14.5862],[-60.9478,14.5593],[-60.9562,14.5509]]]},"properties":{"GID_0":"MTQ","COUNTRY":"Martinique","GID_1":"MTQ.2_1","NAME_1":"LeMarin","NL_NAME_1":"NA","GID_2":"MTQ.2.10_1","NAME_2":"Saint-Esprit","VARNAME_2":"NA","NL_NAME_2":"NA","TYPE_2":"Commune","ENGTYPE_2":"Commune","CC_2":"NA","HASC_2":"MQ.MA.SE"}},
{"type":"Feature","geometry":null,"properties":{"GID_0":"MTQ","COUNTRY":"Martinique","GID_1":"MTQ.2_1","NAME_1":"LeMarin","NL_NAME_1":"NA","GID_2":"MTQ.2.11_1","NAME_2":"Sainte-Anne","VARNAME_2":"NA","NL_NAME_2":"NA","TYPE_2":"Commune","ENGTYPE_2":"Commune","CC_2":"NA","HASC_2":"MQ.MA.SA"}},
{"type":"Feature","geometry":{"type":"MultiPolygon","coordinates":[[[[-60.985,14.4991],[-60.9823,14.4807],[-60.9166,14.4685],[-60.9318,14.4993],[-60.985,14.4991]]],[[[-61.1605,14.8197],[-61.1419,14.8093],[-61.1268,14.825],[-61.0964,14.8334],[-61.126,14.8746],[-61.1605,14.8197]]]]},"properties":{"GID_0":"MTQ","COUNTRY":"Martinique","GID_1":"MTQ.3_1","NAME_1":"LeTrinité","NL_NAME_1":"NA","GID_2":"MTQ.3.1_1","NAME_2":"Basse-Pointe","VARNAME_2":"NA","NL_NAME_2":"NA","TYPE_2":"Commune","ENGTYPE_2":"Commune","CC_2":"NA","HASC_2":"MQ.TR.BP"}},
{"type":"Feature","geometry":{"type":"Polygon","coordinates":[[[-60.9817,14.6915],[-60.9757,14.6988],[-61.0018,14.7294],[-61.0585,14.7406],[-61.082,14.7272],[-61.0864,14.7211],[-61.016,14.6834],[-60.9965,14.6755],[-60.9817,14.6915]]]},"properties":{"GID_0":"MTQ","COUNTRY":"Martinique","GID_1":"MTQ.3_1","NAME_1":"LeTrinité","NL_NAME_1":"NA","GID_2":"MTQ.3.2_1","NAME_2":"Gros-Morne","VARNAME_2":"NA","NL_NAME_2":"NA","TYPE_2":"Commune","ENGTYPE_2":"Commune","CC_2":"NA","HASC_2":"MQ.TR.GM"}},
{"type":"Feature","geometry":{"type":"Polygon","coordinates":[[[-61.1419,14.8093],[-61.1005,14.8143],[-61.0964,14.8334],[-61.1268,14.825],[-61.1419,14.8093]]]},"properties":{"GID_0":"MTQ","COUNTRY":"Martinique","GID_1":"MTQ.3_1","NAME_1":"LeTrinité","NL_NAME_1":"NA","GID_2":"MTQ.3.3_1","NAME_2":"L'Ajoupa-Bouillon","VARNAME_2":"NA","NL_NAME_2":"NA","TYPE_2":"Commune","ENGTYPE_2":"Commune","CC_2":"NA","HASC_2":"MQ.TR.AB"}},
{"type":"Feature","geometry":{"type":"Polygon","coordinates":[[[-60.9757,14.6988],[-60.9335,14.7103],[-60.9738,14.7635],[-61.0018,14.7294],[-60.9757,14.6988]]]},"properties":{"GID_0":"MTQ","COUNTRY":"Martinique","GID_1":"MTQ.3_1","NAME_1":"LeTrinité","NL_NAME_1":"NA","GID_2":"MTQ.3.4_1","NAME_2":"LaTrinité","VARNAME_2":"NA","NL_NAME_2":"NA","TYPE_2":"Commune","ENGTYPE_2":"Commune","CC_2":"NA","HASC_2":"MQ.TR.TR"}},
{"type":"Feature","geometry":{"type":"Polygon","coordinates":[[[-61.0964,14.8334],[-61.1005,14.8143],[-61.1095,14.8093],[-61.0877,14.7536],[-61.0827,14.7461],[-61.0628,14.7679],[-61.0964,14.8334]]]},"properties":{"GID_0":"MTQ","COUNTRY":"Martinique","GID_1":"MTQ.3_1","NAME_1":"LeTrinité","NL_NAME_1":"NA","GID_2":"MTQ.3.5_1","NAME_2":"LeLorrain","VARNAME_2":"NA","NL_NAME_2":"NA","TYPE_2":"Commune","ENGTYPE_2":"Commune","CC_2":"NA","HASC_2":"MQ.TR.LO"}},
{"type":"Feature","geometry":{"type":"Polygon","coordinates":[[[-61.0585,14.7406],[-61.0157,14.8081],[-61.0628,14.7679],[-61.0827,14.7461],[-61.0844,14.7423],[-61.0877,14.74],[-61.0585,14.7406]]]},"properties":{"GID_0":"MTQ","COUNTRY":"Martinique","GID_1":"MTQ.3_1","NAME_1":"LeTrinité","NL_NAME_1":"NA","GID_2":"MTQ.3.6_1","NAME_2":"LeMarigot","VARNAME_2":"NA","NL_NAME_2":"NA","TYPE_2":"Commune","ENGTYPE_2":"Commune","CC_2":"NA","HASC_2":"MQ.TR.MG"}},
{"type":"Feature","geometry":{"type":"Polygon","coordinates":[[[-60.9518,14.6448],[-60.9359,14.6283],[-60.9033,14.6485],[-60.9335,14.7103],[-60.9757,14.6988],[-60.9817,14.6915],[-60.9518,14.6448]]]},"properties":{"GID_0":"MTQ","COUNTRY":"Martinique","GID_1":"MTQ.3_1","NAME_1":"LeTrinité","NL_NAME_1":"NA","GID_2":"MTQ.3.7_1","NAME_2":"LeRobert","VARNAME_2":"NA","NL_NAME_2":"NA","TYPE_2":"Commune","ENGTYPE_2":"Commune","CC_2":"NA","HASC_2":"MQ.TR.RO"}},
{"type":"Feature","geometry":{"type":"Polygon","coordinates":[[[-61.126,14.8746],[-61.1993,14.8632],[-61.1866,14.8224],[-61.126,14.8746]]]},"properties":{"GID_0":"MTQ","COUNTRY":"Martinique","GID_1":"MTQ.3_1","NAME_1":"LeTrinité","NL_NAME_1":"NA","GID_2":"MTQ.3.8_1","NAME_2":"Macouba","VARNAME_2":"NA","NL_NAME_2":"NA","TYPE_2":"Commune","ENGTYPE_2":"Commune","CC_2":"NA","HASC_2":"MQ.TR.MC"}},
{"type":"Feature","geometry":{"type":"Polygon","coordinates":[[[-61.0585,14.7406],[-60.9738,14.7635],[-61.0157,14.8081],[-61.0585,14.7406]]]},"properties":{"GID_0":"MTQ","COUNTRY":"Martinique","GID_1":"MTQ.3_1","NAME_1":"LeTrinité","NL_NAME_1":"NA","GID_2":"MTQ.3.9_1","NAME_2":"Sainte-Marie","VARNAME_2":"NA","NL_NAME_2":"NA","TYPE_2":"Commune","ENGTYPE_2":"Commune","CC_2":"NA","HASC_2":"MQ.TR.SM"}},
{"type":"Feature","geometry":{"type":"Polygon","coordinates":[[[-61.154,14.656],[-61.1237,14.6912],[-61.1569,14.6876],[-61.1693,14.6774],[-61.154,14.656]]]},"properties":{"GID_0":"MTQ","COUNTRY":"Martinique","GID_1":"MTQ.4_1","NAME_1":"Saint-Pierre","NL_NAME_1":"NA","GID_2":"MTQ.4.1_1","NAME_2":"Bellefontaine","VARNAME_2":"NA","NL_NAME_2":"NA","TYPE_2":"Commune","ENGTYPE_2":"Commune","CC_2":"NA","HASC_2":"MQ.SP.BF"}},
{"type":"Feature","geometry":{"type":"Polygon","coordinates":[[[-61.1188,14.6918],[-61.1237,14.6912],[-61.154,14.656],[-61.1249,14.6305],[-61.1116,14.6602],[-61.1095,14.6833],[-61.1188,14.6918]]]},"properties":{"GID_0":"MTQ","COUNTRY":"Martinique","GID_1":"MTQ.4_1","NAME_1":"Saint-Pierre","NL_NAME_1":"NA","GID_2":"MTQ.4.2_1","NAME_2":"Case-Pilote","VARNAME_2":"NA","NL_NAME_2":"NA","TYPE_2":"Commune","ENGTYPE_2":"Commune","CC_2":"NA","HASC_2":"MQ.SP.CP"}},
{"type":"Feature","geometry":{"type":"Polygon","coordinates":[[[-61.0873,14.7081],[-61.0864,14.7211],[-61.082,14.7272],[-61.0877,14.74],[-61.1028,14.7347],[-61.1286,14.7459],[-61.1295,14.7475],[-61.1583,14.7342],[-61.0873,14.7081]]]},"properties":{"GID_0":"MTQ","COUNTRY":"Martinique","GID_1":"MTQ.4_1","NAME_1":"Saint-Pierre","NL_NAME_1":"NA","GID_2":"MTQ.4.3_1","NAME_2":"Fonds-Saint-Denis","VARNAME_2":"NA","NL_NAME_2":"NA","TYPE_2":"Commune","ENGTYPE_2":"Commune","CC_2":"NA","HASC_2":"MQ.SP.FS"}},
{"type":"Feature","geometry":{"type":"Polygon","coordinates":[[[-61.1498,14.6909],[-61.1273,14.7209],[-61.1612,14.7293],[-61.1796,14.7306],[-61.1693,14.6774],[-61.1569,14.6876],[-61.1498,14.6909]]]},"properties":{"GID_0":"MTQ","COUNTRY":"Martinique","GID_1":"MTQ.4_1","NAME_1":"Saint-Pierre","NL_NAME_1":"NA","GID_2":"MTQ.4.4_1","NAME_2":"LeCarbet","VARNAME_2":"NA","NL_NAME_2":"NA","TYPE_2":"Commune","ENGTYPE_2":"Commune","CC_2":"NA","HASC_2":"MQ.SP.CA"}},
{"type":"Feature","geometry":{"type":"Polygon","coordinates":[[[-61.1484,14.8002],[-61.1563,14.7676],[-61.1334,14.7506],[-61.1286,14.7459],[-61.1028,14.7347],[-61.0844,14.7423],[-61.0877,14.7536],[-61.1095,14.8093],[-61.1484,14.8002]]]},"properties":{"GID_0":"MTQ","COUNTRY":"Martinique","GID_1":"MTQ.4_1","NAME_1":"Saint-Pierre","NL_NAME_1":"NA","GID_2":"MTQ.4.5_1","NAME_2":"LeMorne-Rouge","VARNAME_2":"NA","NL_NAME_2":"NA","TYPE_2":"Commune","ENGTYPE_2":"Commune","CC_2":"NA","HASC_2":"MQ.SP.MR"}},
{"type":"Feature","geometry":{"type":"Polygon","coordinates":[[[-61.1102,14.7046],[-61.1273,14.7209],[-61.1498,14.6909],[-61.1102,14.7046]]]},"properties":{"GID_0":"MTQ","COUNTRY":"Martinique","GID_1":"MTQ.4_1","NAME_1":"Saint-Pierre","NL_NAME_1":"NA","GID_2":"MTQ.4.6_1","NAME_2":"LeMorne-Vert","VARNAME_2":"NA","NL_NAME_2":"NA","TYPE_2":"Commune","ENGTYPE_2":"Commune","CC_2":"NA","HASC_2":"MQ.SP.MV"}},
{"type":"Feature","geometry":{"type":"Polygon","coordinates":[[[-61.1993,14.8632],[-61.2137,14.7815],[-61.1665,14.8187],[-61.1866,14.8224],[-61.1993,14.8632]]]},"properties":{"GID_0":"MTQ","COUNTRY":"Martinique","GID_1":"MTQ.4_1","NAME_1":"Saint-Pierre","NL_NAME_1":"NA","GID_2":"MTQ.4.7_1","NAME_2":"LePrêcheur","VARNAME_2":"NA","NL_NAME_2":"NA","TYPE_2":"Commune","ENGTYPE_2":"Commune","CC_2":"NA","HASC_2":"MQ.SP.PR"}},
{"type":"Feature","geometry":{"type":"Polygon","coordinates":[[[-61.1605,14.8197],[-61.1665,14.8187],[-61.2137,14.7815],[-61.1796,14.7306],[-61.1612,14.7293],[-61.1583,14.7342],[-61.1295,14.7475],[-61.1334,14.7506],[-61.1563,14.7676],[-61.1484,14.8002],[-61.1605,14.8197]]]},"properties":{"GID_0":"MTQ","COUNTRY":"Martinique","GID_1":"MTQ.4_1","NAME_1":"Saint-Pierre","NL_NAME_1":"NA","GID_2":"MTQ.4.8_1","NAME_2":"Saint-Pierre","VARNAME_2":"NA","NL_NAME_2":"NA","TYPE_2":"Commune","ENGTYPE_2":"Commune","CC_2":"NA","HASC_2":"MQ.SP.SP"}}
]}
