{"CRI.1.1_1":{"FOI":{"mean":0.0304,"sd":0},"serop9":{"mean":33.6714,"sd":0}},"CRI.1.10_1":{"FOI":{"mean":0.0304,"sd":0},"serop9":{"mean":33.6714,"sd":0}},"CRI.1.11_1":{"FOI":{"mean":0.0236,"sd":0},"serop9":{"mean":42.8805,"sd":0}},"CRI.1.12_1":{"FOI":{"mean":0.0284,"sd":0},"serop9":{"mean":36.0869,"sd":0}},"CRI.1.13_1":{"FOI":{"mean":0.0257,"sd":0},"serop9":{"mean":39.9164,"sd":0}},"CRI.1.14_1":{"FOI":{"mean":0.026,"sd":0},"serop9":{"mean":39.4019,"sd":0}},"CRI.1.15_1":{"FOI":{"mean":0.022,"sd":0},"serop9":{"mean":45.6394,"sd":0}},"CRI.1.16_1":{"FOI":{"mean":0.022,"sd":0},"serop9":{"mean":45.6394,"sd":0}},"CRI.1.17_1":{"FOI":{"mean":0.0222,"sd":0},"serop9":{"mean":45.0944,"sd":0}},"CRI.1.3_1":{"FOI":{"mean":0.0284,"sd":0},"serop9":{"mean":36.0869,"sd":0}},"CRI.1.4_1":{"FOI":{"mean":0.0304,"sd":0},"serop9":{"mean":33.6714,"sd":0}},"CRI.1.5_1":{"FOI":{"mean":0.0238,"sd":0},"serop9":{"mean":42.5568,"sd":0}},"CRI.1.6_1":{"FOI":{"mean":0.0239,"sd":0},"serop9":{"mean":42.393,"sd":0}},"CRI.1.7_1":{"FOI":{"mean":0.022,"sd":0},"serop9":{"mean":45.6394,"sd":0}},"CRI.1.8_1":{"FOI":{"mean":0.0284,"sd":0},"serop9":{"mean":36.0869,"sd":0}},"CRI.1.9_1":{"FOI":{"mean":0.0284,"sd":0},"serop9":{"mean":36.0869,"sd":0}},"CRI.2.1_1":{"FOI":{"mean":0.0239,"sd":0},"serop9":{"mean":42.7461,"sd":0}},"CRI.2.2_1":{"FOI":{"mean":0.0209,"sd":0},"serop9":{"mean":47.4246,"sd":0}},"CRI.2.3_1":{"FOI":{"mean":0.022,"sd":0},"serop9":{"mean":45.5093,"sd":0}},"CRI.2.4_1":{"FOI":{"mean":0.0246,"sd":0},"serop9":{"mean":41.447,"sd":0}},"CRI.2.5_1":{"FOI":{"mean":0.0209,"sd":0},"serop9":{"mean":47.4246,"sd":0}},"CRI.2.6_1":{"FOI":{"mean":0.0239,"sd":0},"serop9":{"mean":42.7461,"sd":0}},"CRI.2.7_1":{"FOI":{"mean":0.0242,"sd":0},"serop9":{"mean":42.1938,"sd":0}},"CRI.2.8_1":{"FOI":{"mean":0.0246,"sd":0},"serop9":{"mean":41.3506,"sd":0}},"CRI.3.1_1":{"FOI":{"mean":0.0265,"sd":0},"serop9":{"mean":38.6743,"sd":0}},"CRI.3.10_1":{"FOI":{"mean":0.0288,"sd":0},"serop9":{"mean":35.6125,"sd":0}},"CRI.3.11_1":{"FOI":{"mean":0.026,"sd":0},"serop9":{"mean":39.3177,"sd":0}},"CRI.3.2_1":{"FOI":{"mean":0.027,"sd":0},"serop9":{"mean":37.984,"sd":0}},"CRI.3.3_1":{"FOI":{"mean":0.0298,"sd":0},"serop9":{"mean":34.2422,"sd":0}},"CRI.3.4_1":{"FOI":{"mean":0.0289,"sd":0},"serop9":{"mean":35.4057,"sd":0}},"CRI.3.5_1":{"FOI":{"mean":0.0305,"sd":0},"serop9":{"mean":33.5026,"sd":0}},"CRI.3.6_1":{"FOI":{"mean":0.028,"sd":0},"serop9":{"mean":36.6379,"sd":0}},"CRI.3.7_1":{"FOI":{"mean":0.0299,"sd":0},"serop9":{"mean":34.1766,"sd":0}},"CRI.3.8_1":{"FOI":{"mean":0.0298,"sd":0},"serop9":{"mean":34.2783,"sd":0}},"CRI.3.9_1":{"FOI":{"mean":0.0305,"sd":0},"serop9":{"mean":33.5026,"sd":0}},"CRI.4.1_1":{"FOI":{"mean":0.0263,"sd":0},"serop9":{"mean":38.9956,"sd":0}},"CRI.4.10_1":{"FOI":{"mean":0.0217,"sd":0},"serop9":{"mean":45.9158,"sd":0}},"CRI.4.2_1":{"FOI":{"mean":0.0263,"sd":0},"serop9":{"mean":38.9956,"sd":0}},"CRI.4.3_1":{"FOI":{"mean":0.0263,"sd":0},"serop9":{"mean":38.9956,"sd":0}},"CRI.4.4_1":{"FOI":{"mean":0.0197,"sd":0},"serop9":{"mean":49.2871,"sd":0}},"CRI.4.5_1":{"FOI":{"mean":0.019,"sd":0},"serop9":{"mean":50.8783,"sd":0}},"CRI.4.6_1":{"FOI":{"mean":0.0263,"sd":0},"serop9":{"mean":38.9956,"sd":0}},"CRI.4.7_1":{"FOI":{"mean":0.0263,"sd":0},"serop9":{"mean":38.9956,"sd":0}},"CRI.4.8_1":{"FOI":{"mean":0.0263,"sd":0},"serop9":{"mean":38.9956,"sd":0}},"CRI.4.9_1":{"FOI":{"mean":0.0263,"sd":0},"serop9":{"mean":38.9956,"sd":0}},"CRI.5.1_1":{"FOI":{"mean":0.0228,"sd":0},"serop9":{"mean":44.1144,"sd":0}},"CRI.5.2_1":{"FOI":{"mean":0.0276,"sd":0},"serop9":{"mean":37.2065,"sd":0}},"CRI.5.3_1":{"FOI":{"mean":0.0267,"sd":0},"serop9":{"mean":38.4049,"sd":0}},"CRI.5.4_1":{"FOI":{"mean":0.0228,"sd":0},"serop9":{"mean":44.1466,"sd":0}},"CRI.5.5_1":{"FOI":{"mean":0.0251,"sd":0},"serop9":{"mean":40.7035,"sd":0}},"CRI.5.6_1":{"FOI":{"mean":0.0233,"sd":0},"serop9":{"mean":43.3932,"sd":0}},"CRI.6.10_1":{"FOI":{"mean":0.0243,"sd":0},"serop9":{"mean":41.9495,"sd":0}},"CRI.6.11_1":{"FOI":{"mean":0.0295,"sd":0},"serop9":{"mean":34.7029,"sd":0}},"CRI.6.12_1":{"FOI":{"mean":0.0249,"sd":0},"serop9":{"mean":41.1004,"sd":0}},"CRI.6.2_1":{"FOI":{"mean":0.0254,"sd":0},"serop9":{"mean":40.2717,"sd":0}},"CRI.6.3_1":{"FOI":{"mean":0.0282,"sd":0},"serop9":{"mean":36.4887,"sd":0}},"CRI.6.4_1":{"FOI":{"mean":0.0263,"sd":0},"serop9":{"mean":39.0302,"sd":0}},"CRI.6.5_1":{"FOI":{"mean":0.0273,"sd":0},"serop9":{"mean":37.5542,"sd":0}},"CRI.6.6_1":{"FOI":{"mean":0.0281,"sd":0},"serop9":{"mean":36.5195,"sd":0}},"CRI.6.7_1":{"FOI":{"mean":0.0241,"sd":0},"serop9":{"mean":42.4171,"sd":0}},"CRI.6.8_1":{"FOI":{"mean":0.028,"sd":0},"serop9":{"mean":37.0741,"sd":0}},"CRI.6.9_1":{"FOI":{"mean":0.0261,"sd":0},"serop9":{"mean":39.3138,"sd":0}},"CRI.7.1_1":{"FOI":{"mean":0.0273,"sd":0},"serop9":{"mean":37.5954,"sd":0}},"CRI.7.10_1":{"FOI":{"mean":0.019,"sd":0},"serop9":{"mean":50.8783,"sd":0}},"CRI.7.11_1":{"FOI":{"mean":0.0273,"sd":0},"serop9":{"mean":37.5954,"sd":0}},"CRI.7.12_1":{"FOI":{"mean":0.019,"sd":0},"serop9":{"mean":50.8783,"sd":0}},"CRI.7.13_1":{"FOI":{"mean":0.0278,"sd":0},"serop9":{"mean":36.9795,"sd":0}},"CRI.7.14_1":{"FOI":{"mean":0.0303,"sd":0},"serop9":{"mean":33.796,"sd":0}},"CRI.7.15_1":{"FOI":{"mean":0.0263,"sd":0},"serop9":{"mean":38.9956,"sd":0}},"CRI.7.16_1":{"FOI":{"mean":0.0263,"sd":0},"serop9":{"mean":38.9956,"sd":0}},"CRI.7.17_1":{"FOI":{"mean":0.0232,"sd":0},"serop9":{"mean":43.6289,"sd":0}},"CRI.7.18_1":{"FOI":{"mean":0.0263,"sd":0},"serop9":{"mean":38.9956,"sd":0}},"CRI.7.19_1":{"FOI":{"mean":0.0294,"sd":0},"serop9":{"mean":34.865,"sd":0}},"CRI.7.2_1":{"FOI":{"mean":0.0263,"sd":0},"serop9":{"mean":38.9956,"sd":0}},"CRI.7.20_1":{"FOI":{"mean":0.019,"sd":0},"serop9":{"mean":50.8783,"sd":0}},"CRI.7.3_1":{"FOI":{"mean":0.0225,"sd":0},"serop9":{"mean":44.7863,"sd":0}},"CRI.7.4_1":{"FOI":{"mean":0.0209,"sd":0},"serop9":{"mean":47.4246,"sd":0}},"CRI.7.5_1":{"FOI":{"mean":0.0225,"sd":0},"serop9":{"mean":44.7863,"sd":0}},"CRI.7.6_1":{"FOI":{"mean":0.0232,"sd":0},"serop9":{"mean":43.6289,"sd":0}},"CRI.7.7_1":{"FOI":{"mean":0.0263,"sd":0},"serop9":{"mean":38.9956,"sd":0}},"CRI.7.8_1":{"FOI":{"mean":0.019,"sd":0},"serop9":{"mean":50.8783,"sd":0}},"CRI.7.9_1":{"FOI":{"mean":0.0225,"sd":0},"serop9":{"mean":44.7863,"sd":0}}}
