{"TCD.1.1_1":{"FOI":{"mean":0.0234,"sd":0.0077},"serop9":{"mean":18.8137,"sd":5.6561},"serop9_class":{"mean":18.8137,"sd":5.6561},"hosp_total":{"mean":65.2308,"sd":27.253},"hosp_0_4":{"mean":9.189,"sd":4.1591},"hosp_5_9":{"mean":9.2318,"sd":4.2519},"hosp_10_14":{"mean":8.7776,"sd":4.0107},"hosp_15_19":{"mean":7.8911,"sd":3.5249},"hosp_20_24":{"mean":6.7418,"sd":2.9172},"hosp_25_29":{"mean":5.5275,"sd":2.3025},"hosp_30_34":{"mean":4.4353,"sd":1.7706},"hosp_35_39":{"mean":3.4566,"sd":1.3179},"hosp_40_44":{"mean":2.6406,"sd":0.959},"hosp_45_49":{"mean":2.0003,"sd":0.6905},"hosp_50_54":{"mean":1.5906,"sd":0.5211},"hosp_55_59":{"mean":1.2793,"sd":0.3974},"hosp_60_64":{"mean":0.9921,"sd":0.2921},"hosp_65_69":{"mean":0.6362,"sd":0.1776},"hosp_70_74":{"mean":0.4317,"sd":0.1144},"hosp_75_79":{"mean":0.2513,"sd":0.0634},"hosp_80_84":{"mean":0.1138,"sd":0.0274},"hosp_85_89":{"mean":0.0373,"sd":0.0086},"hosp_90_94":{"mean":0.0071,"sd":0.0016},"hosp_95_99":{"mean":0,"sd":0}},"TCD.10.1_1":{"FOI":{"mean":0.0343,"sd":0.0065},"serop9":{"mean":26.4232,"sd":4.3521},"serop9_class":{"mean":26.4232,"sd":4.3521},"hosp_total":{"mean":96.6622,"sd":25.7044},"hosp_0_4":{"mean":13.9426,"sd":4.4971},"hosp_5_9":{"mean":14.468,"sd":4.5159},"hosp_10_14":{"mean":13.7729,"sd":4.1241},"hosp_15_19":{"mean":12.2237,"sd":3.4762},"hosp_20_24":{"mean":10.2327,"sd":2.743},"hosp_25_29":{"mean":8.1836,"sd":2.0563},"hosp_30_34":{"mean":6.3868,"sd":1.4983},"hosp_35_39":{"mean":4.832,"sd":1.0559},"hosp_40_44":{"mean":3.5786,"sd":0.7282},"hosp_45_49":{"mean":2.6256,"sd":0.4986},"hosp_50_54":{"mean":2.0208,"sd":0.3602},"hosp_55_59":{"mean":1.5724,"sd":0.2657},"hosp_60_64":{"mean":1.1793,"sd":0.1917},"hosp_65_69":{"mean":0.7311,"sd":0.1165},"hosp_70_74":{"mean":0.4796,"sd":0.0765},"hosp_75_79":{"mean":0.2699,"sd":0.044},"hosp_80_84":{"mean":0.1181,"sd":0.02},"hosp_85_89":{"mean":0.0374,"sd":0.0067},"hosp_90_94":{"mean":0.0069,"sd":0.0013},"hosp_95_99":{"mean":0,"sd":0}},"TCD.10.2_1":{"FOI":{"mean":0.0294,"sd":0.0086},"serop9":{"mean":23.0404,"sd":6.0727},"serop9_class":{"mean":23.0404,"sd":6.0727},"hosp_total":{"mean":82.7819,"sd":30.5434},"hosp_0_4":{"mean":11.8317,"sd":4.9208},"hosp_5_9":{"mean":12.139,"sd":5.0711},"hosp_10_14":{"mean":11.5541,"sd":4.7312},"hosp_15_19":{"mean":10.3041,"sd":4.0764},"hosp_20_24":{"mean":8.6909,"sd":3.2918},"hosp_25_29":{"mean":7.0147,"sd":2.5279},"hosp_30_34":{"mean":5.5313,"sd":1.8879},"hosp_35_39":{"mean":4.2316,"sd":1.3632},"hosp_40_44":{"mean":3.171,"sd":0.9618},"hosp_45_49":{"mean":2.3553,"sd":0.6716},"hosp_50_54":{"mean":1.8359,"sd":0.492},"hosp_55_59":{"mean":1.4473,"sd":0.3649},"hosp_60_64":{"mean":1.1001,"sd":0.2618},"hosp_65_69":{"mean":0.6914,"sd":0.1561},"hosp_70_74":{"mean":0.4599,"sd":0.0993},"hosp_75_79":{"mean":0.2625,"sd":0.0548},"hosp_80_84":{"mean":0.1165,"sd":0.0238},"hosp_85_89":{"mean":0.0375,"sd":0.0076},"hosp_90_94":{"mean":0.007,"sd":0.0014},"hosp_95_99":{"mean":0,"sd":0}},"TCD.11.1_1":{"FOI":{"mean":0.0495,"sd":0.0059},"serop9":{"mean":35.8484,"sd":3.3398},"serop9_class":{"mean":35.8484,"sd":3.3398},"hosp_total":{"mean":135.8438,"sd":24.817},"hosp_0_4":{"mean":21.1134,"sd":5.0385},"hosp_5_9":{"mean":22.521,"sd":4.7906},"hosp_10_14":{"mean":21.0859,"sd":4.1598},"hosp_15_19":{"mean":18.0936,"sd":3.342},"hosp_20_24":{"mean":14.5234,"sd":2.5318},"hosp_25_29":{"mean":11.0866,"sd":1.8445},"hosp_30_34":{"mean":8.2368,"sd":1.3273},"hosp_35_39":{"mean":5.9226,"sd":0.9408},"hosp_40_44":{"mean":4.1648,"sd":0.6643},"hosp_45_49":{"mean":2.8997,"sd":0.4726},"hosp_50_54":{"mean":2.1174,"sd":0.3576},"hosp_55_59":{"mean":1.563,"sd":0.2765},"hosp_60_64":{"mean":1.1123,"sd":0.2074},"hosp_65_69":{"mean":0.6546,"sd":0.1292},"hosp_70_74":{"mean":0.4077,"sd":0.0852},"hosp_75_79":{"mean":0.218,"sd":0.0482},"hosp_80_84":{"mean":0.0907,"sd":0.0212},"hosp_85_89":{"mean":0.0274,"sd":0.0067},"hosp_90_94":{"mean":0.0048,"sd":0.0012},"hosp_95_99":{"mean":0,"sd":0}},"TCD.11.2_1":{"FOI":{"mean":0.0476,"sd":0.007},"serop9":{"mean":34.6963,"sd":4.0852},"serop9_class":{"mean":34.6963,"sd":4.0852},"hosp_total":{"mean":130.9166,"sd":25.6495},"hosp_0_4":{"mean":20.1691,"sd":5.2063},"hosp_5_9":{"mean":21.4546,"sd":5.0636},"hosp_10_14":{"mean":20.1283,"sd":4.4057},"hosp_15_19":{"mean":17.3398,"sd":3.5143},"hosp_20_24":{"mean":13.9871,"sd":2.6283},"hosp_25_29":{"mean":10.7371,"sd":1.884},"hosp_30_34":{"mean":8.0255,"sd":1.3333},"hosp_35_39":{"mean":5.8079,"sd":0.9325},"hosp_40_44":{"mean":4.1116,"sd":0.654},"hosp_45_49":{"mean":2.8826,"sd":0.4661},"hosp_50_54":{"mean":2.12,"sd":0.3562},"hosp_55_59":{"mean":1.5764,"sd":0.2798},"hosp_60_64":{"mean":1.1302,"sd":0.214},"hosp_65_69":{"mean":0.6701,"sd":0.1361},"hosp_70_74":{"mean":0.4206,"sd":0.0917},"hosp_75_79":{"mean":0.2266,"sd":0.0529},"hosp_80_84":{"mean":0.095,"sd":0.0237},"hosp_85_89":{"mean":0.0289,"sd":0.0077},"hosp_90_94":{"mean":0.0051,"sd":0.0014},"hosp_95_99":{"mean":0,"sd":0}},"TCD.11.3_1":{"FOI":{"mean":0.049,"sd":0.0079},"serop9":{"mean":35.5077,"sd":4.5589},"serop9_class":{"mean":35.5077,"sd":4.5589},"hosp_total":{"mean":134.2744,"sd":27.6747},"hosp_0_4":{"mean":20.9151,"sd":5.7092},"hosp_5_9":{"mean":22.2801,"sd":5.6298},"hosp_10_14":{"mean":20.8319,"sd":4.8727},"hosp_15_19":{"mean":17.857,"sd":3.8377},"hosp_20_24":{"mean":14.3245,"sd":2.8224},"hosp_25_29":{"mean":10.933,"sd":1.9848},"hosp_30_34":{"mean":8.1251,"sd":1.3781},"hosp_35_39":{"mean":5.8468,"sd":0.9483},"hosp_40_44":{"mean":4.1165,"sd":0.6582},"hosp_45_49":{"mean":2.8709,"sd":0.4674},"hosp_50_54":{"mean":2.1007,"sd":0.358},"hosp_55_59":{"mean":1.5546,"sd":0.2828},"hosp_60_64":{"mean":1.1095,"sd":0.2178},"hosp_65_69":{"mean":0.655,"sd":0.1393},"hosp_70_74":{"mean":0.4095,"sd":0.0943},"hosp_75_79":{"mean":0.2198,"sd":0.0547},"hosp_80_84":{"mean":0.0918,"sd":0.0246},"hosp_85_89":{"mean":0.0278,"sd":0.008},"hosp_90_94":{"mean":0.0049,"sd":0.0015},"hosp_95_99":{"mean":0,"sd":0}},"TCD.12.1_1":{"FOI":{"mean":0.0521,"sd":0.0079},"serop9":{"mean":37.2611,"sd":4.3969},"serop9_class":{"mean":37.2611,"sd":4.3969},"hosp_total":{"mean":141.4974,"sd":27.9736},"hosp_0_4":{"mean":22.4443,"sd":5.9291},"hosp_5_9":{"mean":23.9779,"sd":5.7802},"hosp_10_14":{"mean":22.3019,"sd":4.945},"hosp_15_19":{"mean":18.9625,"sd":3.8563},"hosp_20_24":{"mean":15.0688,"sd":2.8175},"hosp_25_29":{"mean":11.3858,"sd":1.9779},"hosp_30_34":{"mean":8.3737,"sd":1.3785},"hosp_35_39":{"mean":5.962,"sd":0.9563},"hosp_40_44":{"mean":4.1529,"sd":0.67},"hosp_45_49":{"mean":2.8654,"sd":0.4787},"hosp_50_54":{"mean":2.0744,"sd":0.367},"hosp_55_59":{"mean":1.5189,"sd":0.2884},"hosp_60_64":{"mean":1.0727,"sd":0.22},"hosp_65_69":{"mean":0.6268,"sd":0.139},"hosp_70_74":{"mean":0.3879,"sd":0.0928},"hosp_75_79":{"mean":0.2061,"sd":0.053},"hosp_80_84":{"mean":0.0853,"sd":0.0235},"hosp_85_89":{"mean":0.0256,"sd":0.0075},"hosp_90_94":{"mean":0.0045,"sd":0.0014},"hosp_95_99":{"mean":0,"sd":0}},"TCD.12.2_1":{"FOI":{"mean":0.056,"sd":0.0057},"serop9":{"mean":39.5345,"sd":3.0604},"serop9_class":{"mean":39.5345,"sd":3.0604},"hosp_total":{"mean":150.9947,"sd":26.635},"hosp_0_4":{"mean":24.4368,"sd":5.5483},"hosp_5_9":{"mean":26.2243,"sd":5.2557},"hosp_10_14":{"mean":24.2574,"sd":4.5184},"hosp_15_19":{"mean":20.4353,"sd":3.5891},"hosp_20_24":{"mean":16.0583,"sd":2.6913},"hosp_25_29":{"mean":11.9837,"sd":1.9441},"hosp_30_34":{"mean":8.6972,"sd":1.3886},"hosp_35_39":{"mean":6.1068,"sd":0.9766},"hosp_40_44":{"mean":4.1929,"sd":0.6827},"hosp_45_49":{"mean":2.8505,"sd":0.4791},"hosp_50_54":{"mean":2.0327,"sd":0.3564},"hosp_55_59":{"mean":1.4658,"sd":0.2699},"hosp_60_64":{"mean":1.0194,"sd":0.1978},"hosp_65_69":{"mean":0.5865,"sd":0.1201},"hosp_70_74":{"mean":0.3574,"sd":0.0772},"hosp_75_79":{"mean":0.187,"sd":0.0426},"hosp_80_84":{"mean":0.0762,"sd":0.0182},"hosp_85_89":{"mean":0.0225,"sd":0.0056},"hosp_90_94":{"mean":0.0039,"sd":0.001},"hosp_95_99":{"mean":0,"sd":0}},"TCD.12.3_1":{"FOI":{"mean":0.0528,"sd":0.0064},"serop9":{"mean":37.6982,"sd":3.5708},"serop9_class":{"mean":37.6982,"sd":3.5708},"hosp_total":{"mean":143.3784,"sd":26.1258},"hosp_0_4":{"mean":22.7614,"sd":5.4561},"hosp_5_9":{"mean":24.3501,"sd":5.1921},"hosp_10_14":{"mean":22.6541,"sd":4.4615},"hosp_15_19":{"mean":19.2551,"sd":3.5351},"hosp_20_24":{"mean":15.2883,"sd":2.6414},"hosp_25_29":{"mean":11.5369,"sd":1.9019},"hosp_30_34":{"mean":8.4708,"sd":1.3573},"hosp_35_39":{"mean":6.019,"sd":0.9576},"hosp_40_44":{"mean":4.1828,"sd":0.6752},"hosp_45_49":{"mean":2.8783,"sd":0.4803},"hosp_50_54":{"mean":2.0777,"sd":0.3636},"hosp_55_59":{"mean":1.5165,"sd":0.2808},"hosp_60_64":{"mean":1.0673,"sd":0.2103},"hosp_65_69":{"mean":0.6214,"sd":0.1304},"hosp_70_74":{"mean":0.3831,"sd":0.0856},"hosp_75_79":{"mean":0.2028,"sd":0.0481},"hosp_80_84":{"mean":0.0836,"sd":0.021},"hosp_85_89":{"mean":0.025,"sd":0.0066},"hosp_90_94":{"mean":0.0043,"sd":0.0012},"hosp_95_99":{"mean":0,"sd":0}},"TCD.12.4_1":{"FOI":{"mean":0.0538,"sd":0.0073},"serop9":{"mean":38.269,"sd":4.0083},"serop9_class":{"mean":38.269,"sd":4.0083},"hosp_total":{"mean":145.6765,"sd":27.6368},"hosp_0_4":{"mean":23.3283,"sd":5.884},"hosp_5_9":{"mean":24.9654,"sd":5.6719},"hosp_10_14":{"mean":23.1583,"sd":4.8388},"hosp_15_19":{"mean":19.6065,"sd":3.7787},"hosp_20_24":{"mean":15.5014,"sd":2.7735},"hosp_25_29":{"mean":11.6475,"sd":1.9609},"hosp_30_34":{"mean":8.5159,"sd":1.3776},"hosp_35_39":{"mean":6.0263,"sd":0.9618},"hosp_40_44":{"mean":4.1714,"sd":0.6753},"hosp_45_49":{"mean":2.8598,"sd":0.4811},"hosp_50_54":{"mean":2.057,"sd":0.3661},"hosp_55_59":{"mean":1.4965,"sd":0.2848},"hosp_60_64":{"mean":1.05,"sd":0.2147},"hosp_65_69":{"mean":0.6096,"sd":0.1341},"hosp_70_74":{"mean":0.3748,"sd":0.0885},"hosp_75_79":{"mean":0.1979,"sd":0.05},"hosp_80_84":{"mean":0.0814,"sd":0.0219},"hosp_85_89":{"mean":0.0243,"sd":0.0069},"hosp_90_94":{"mean":0.0042,"sd":0.0013},"hosp_95_99":{"mean":0,"sd":0}},"TCD.13.1_1":{"FOI":{"mean":0.0579,"sd":0.0069},"serop9":{"mean":40.4953,"sd":3.6268},"serop9_class":{"mean":40.4953,"sd":3.6268},"hosp_total":{"mean":154.7684,"sd":28.1105},"hosp_0_4":{"mean":25.4015,"sd":6.0773},"hosp_5_9":{"mean":27.2644,"sd":5.7916},"hosp_10_14":{"mean":25.0968,"sd":4.905},"hosp_15_19":{"mean":21.0083,"sd":3.815},"hosp_20_24":{"mean":16.3957,"sd":2.7998},"hosp_25_29":{"mean":12.1506,"sd":1.9861},"hosp_30_34":{"mean":8.7578,"sd":1.4017},"hosp_35_39":{"mean":6.1081,"sd":0.9812},"hosp_40_44":{"mean":4.1666,"sd":0.6875},"hosp_45_49":{"mean":2.815,"sd":0.4858},"hosp_50_54":{"mean":1.9956,"sd":0.3646},"hosp_55_59":{"mean":1.431,"sd":0.2786},"hosp_60_64":{"mean":0.9899,"sd":0.2059},"hosp_65_69":{"mean":0.5667,"sd":0.1259},"hosp_70_74":{"mean":0.3437,"sd":0.0813},"hosp_75_79":{"mean":0.1791,"sd":0.045},"hosp_80_84":{"mean":0.0727,"sd":0.0193},"hosp_85_89":{"mean":0.0214,"sd":0.006},"hosp_90_94":{"mean":0.0037,"sd":0.0011},"hosp_95_99":{"mean":0,"sd":0}},"TCD.13.2_1":{"FOI":{"mean":0.0506,"sd":0.0087},"serop9":{"mean":36.4024,"sd":4.8805},"serop9_class":{"mean":36.4024,"sd":4.8805},"hosp_total":{"mean":137.9152,"sd":28.8003},"hosp_0_4":{"mean":21.7285,"sd":6.1004},"hosp_5_9":{"mean":23.1735,"sd":6.0184},"hosp_10_14":{"mean":21.5897,"sd":5.1573},"hosp_15_19":{"mean":18.4124,"sd":4.0096},"hosp_20_24":{"mean":14.6864,"sd":2.9093},"hosp_25_29":{"mean":11.1437,"sd":2.0216},"hosp_30_34":{"mean":8.2331,"sd":1.3921},"hosp_35_39":{"mean":5.8903,"sd":0.9554},"hosp_40_44":{"mean":4.1237,"sd":0.6653},"hosp_45_49":{"mean":2.8602,"sd":0.4757},"hosp_50_54":{"mean":2.0818,"sd":0.367},"hosp_55_59":{"mean":1.5328,"sd":0.2914},"hosp_60_64":{"mean":1.0886,"sd":0.225},"hosp_65_69":{"mean":0.6397,"sd":0.1439},"hosp_70_74":{"mean":0.3981,"sd":0.0972},"hosp_75_79":{"mean":0.2128,"sd":0.0562},"hosp_80_84":{"mean":0.0885,"sd":0.0251},"hosp_85_89":{"mean":0.0267,"sd":0.0081},"hosp_90_94":{"mean":0.0047,"sd":0.0015},"hosp_95_99":{"mean":0,"sd":0}},"TCD.13.3_1":{"FOI":{"mean":0.0527,"sd":0.0069},"serop9":{"mean":37.6659,"sd":3.8107},"serop9_class":{"mean":37.6659,"sd":3.8107},"hosp_total":{"mean":143.2797,"sd":27.103},"hosp_0_4":{"mean":22.7731,"sd":5.7247},"hosp_5_9":{"mean":24.3513,"sd":5.4846},"hosp_10_14":{"mean":22.6434,"sd":4.6935},"hosp_15_19":{"mean":19.237,"sd":3.6886},"hosp_20_24":{"mean":15.2682,"sd":2.7275},"hosp_25_29":{"mean":11.5186,"sd":1.9417},"hosp_30_34":{"mean":8.4559,"sd":1.371},"hosp_35_39":{"mean":6.0079,"sd":0.9593},"hosp_40_44":{"mean":4.1752,"sd":0.6732},"hosp_45_49":{"mean":2.8734,"sd":0.4784},"hosp_50_54":{"mean":2.0746,"sd":0.3628},"hosp_55_59":{"mean":1.5146,"sd":0.2813},"hosp_60_64":{"mean":1.0664,"sd":0.2116},"hosp_65_69":{"mean":0.6211,"sd":0.1319},"hosp_70_74":{"mean":0.3831,"sd":0.087},"hosp_75_79":{"mean":0.2029,"sd":0.0491},"hosp_80_84":{"mean":0.0837,"sd":0.0215},"hosp_85_89":{"mean":0.025,"sd":0.0068},"hosp_90_94":{"mean":0.0043,"sd":0.0012},"hosp_95_99":{"mean":0,"sd":0}},"TCD.14.1_1":{"FOI":{"mean":0.0499,"sd":0.0064},"serop9":{"mean":36.0629,"sd":3.6712},"serop9_class":{"mean":36.0629,"sd":3.6712},"hosp_total":{"mean":136.7813,"sd":26.5842},"hosp_0_4":{"mean":21.3527,"sd":5.4202},"hosp_5_9":{"mean":22.7775,"sd":5.2354},"hosp_10_14":{"mean":21.2962,"sd":4.5428},"hosp_15_19":{"mean":18.24,"sd":3.6209},"hosp_20_24":{"mean":14.6112,"sd":2.7077},"hosp_25_29":{"mean":11.1308,"sd":1.9392},"hosp_30_34":{"mean":8.2528,"sd":1.3683},"hosp_35_39":{"mean":5.9226,"sd":0.9508},"hosp_40_44":{"mean":4.157,"sd":0.66},"hosp_45_49":{"mean":2.8893,"sd":0.4638},"hosp_50_54":{"mean":2.1063,"sd":0.349},"hosp_55_59":{"mean":1.5526,"sd":0.2698},"hosp_60_64":{"mean":1.1034,"sd":0.2034},"hosp_65_69":{"mean":0.6485,"sd":0.1277},"hosp_70_74":{"mean":0.4035,"sd":0.0851},"hosp_75_79":{"mean":0.2156,"sd":0.0487},"hosp_80_84":{"mean":0.0896,"sd":0.0217},"hosp_85_89":{"mean":0.027,"sd":0.007},"hosp_90_94":{"mean":0.0047,"sd":0.0013},"hosp_95_99":{"mean":0,"sd":0}},"TCD.14.2_1":{"FOI":{"mean":0.0507,"sd":0.0062},"serop9":{"mean":36.5146,"sd":3.5091},"serop9_class":{"mean":36.5146,"sd":3.5091},"hosp_total":{"mean":138.627,"sd":26.0808},"hosp_0_4":{"mean":21.7265,"sd":5.3615},"hosp_5_9":{"mean":23.1976,"sd":5.1443},"hosp_10_14":{"mean":21.665,"sd":4.4457},"hosp_15_19":{"mean":18.5222,"sd":3.5368},"hosp_20_24":{"mean":14.8053,"sd":2.6467},"hosp_25_29":{"mean":11.2523,"sd":1.9026},"hosp_30_34":{"mean":8.3226,"sd":1.3515},"hosp_35_39":{"mean":5.9577,"sd":0.9474},"hosp_40_44":{"mean":4.1709,"sd":0.6636},"hosp_45_49":{"mean":2.8914,"sd":0.4698},"hosp_50_54":{"mean":2.1023,"sd":0.355},"hosp_55_59":{"mean":1.5455,"sd":0.2745},"hosp_60_64":{"mean":1.0955,"sd":0.2064},"hosp_65_69":{"mean":0.6422,"sd":0.1288},"hosp_70_74":{"mean":0.3985,"sd":0.0852},"hosp_75_79":{"mean":0.2123,"sd":0.0483},"hosp_80_84":{"mean":0.0881,"sd":0.0213},"hosp_85_89":{"mean":0.0265,"sd":0.0068},"hosp_90_94":{"mean":0.0046,"sd":0.0012},"hosp_95_99":{"mean":0,"sd":0}},"TCD.14.3_1":{"FOI":{"mean":0.053,"sd":0.0064},"serop9":{"mean":37.8382,"sd":3.5646},"serop9_class":{"mean":37.8382,"sd":3.5646},"hosp_total":{"mean":144.004,"sd":26.6906},"hosp_0_4":{"mean":22.9037,"sd":5.573},"hosp_5_9":{"mean":24.5076,"sd":5.3278},"hosp_10_14":{"mean":22.7879,"sd":4.5789},"hosp_15_19":{"mean":19.3527,"sd":3.621},"hosp_20_24":{"mean":15.3511,"sd":2.695},"hosp_25_29":{"mean":11.5724,"sd":1.9294},"hosp_30_34":{"mean":8.4878,"sd":1.3671},"hosp_35_39":{"mean":6.0246,"sd":0.9573},"hosp_40_44":{"mean":4.1821,"sd":0.6704},"hosp_45_49":{"mean":2.8748,"sd":0.4745},"hosp_50_54":{"mean":2.0729,"sd":0.3581},"hosp_55_59":{"mean":1.5115,"sd":0.2763},"hosp_60_64":{"mean":1.0628,"sd":0.207},"hosp_65_69":{"mean":0.6181,"sd":0.1286},"hosp_70_74":{"mean":0.3807,"sd":0.0846},"hosp_75_79":{"mean":0.2014,"sd":0.0478},"hosp_80_84":{"mean":0.0829,"sd":0.0209},"hosp_85_89":{"mean":0.0248,"sd":0.0066},"hosp_90_94":{"mean":0.0043,"sd":0.0012},"hosp_95_99":{"mean":0,"sd":0}},"TCD.15.1_1":{"FOI":{"mean":0.0489,"sd":0.0091},"serop9":{"mean":35.3785,"sd":5.2238},"serop9_class":{"mean":35.3785,"sd":5.2238},"hosp_total":{"mean":133.6052,"sd":29.2454},"hosp_0_4":{"mean":20.8661,"sd":6.1356},"hosp_5_9":{"mean":22.2058,"sd":6.1093},"hosp_10_14":{"mean":20.7354,"sd":5.2596},"hosp_15_19":{"mean":17.7537,"sd":4.0971},"hosp_20_24":{"mean":14.2289,"sd":2.9703},"hosp_25_29":{"mean":10.8538,"sd":2.0554},"hosp_30_34":{"mean":8.0642,"sd":1.4049},"hosp_35_39":{"mean":5.8034,"sd":0.9556},"hosp_40_44":{"mean":4.0875,"sd":0.6604},"hosp_45_49":{"mean":2.8526,"sd":0.4708},"hosp_50_54":{"mean":2.0894,"sd":0.3641},"hosp_55_59":{"mean":1.5481,"sd":0.2911},"hosp_60_64":{"mean":1.1065,"sd":0.2269},"hosp_65_69":{"mean":0.6543,"sd":0.1466},"hosp_70_74":{"mean":0.4098,"sd":0.1001},"hosp_75_79":{"mean":0.2204,"sd":0.0584},"hosp_80_84":{"mean":0.0923,"sd":0.0264},"hosp_85_89":{"mean":0.028,"sd":0.0086},"hosp_90_94":{"mean":0.0049,"sd":0.0016},"hosp_95_99":{"mean":0,"sd":0}},"TCD.15.2_1":{"FOI":{"mean":0.0512,"sd":0.0067},"serop9":{"mean":36.8263,"sd":3.7549},"serop9_class":{"mean":36.8263,"sd":3.7549},"hosp_total":{"mean":139.814,"sd":26.2023},"hosp_0_4":{"mean":21.9985,"sd":5.426},"hosp_5_9":{"mean":23.5014,"sd":5.2114},"hosp_10_14":{"mean":21.9207,"sd":4.4948},"hosp_15_19":{"mean":18.7061,"sd":3.5644},"hosp_20_24":{"mean":14.9216,"sd":2.6592},"hosp_25_29":{"mean":11.3168,"sd":1.9082},"hosp_30_34":{"mean":8.3527,"sd":1.3558},"hosp_35_39":{"mean":5.9669,"sd":0.9528},"hosp_40_44":{"mean":4.1691,"sd":0.6702},"hosp_45_49":{"mean":2.8847,"sd":0.4769},"hosp_50_54":{"mean":2.0937,"sd":0.3621},"hosp_55_59":{"mean":1.5365,"sd":0.2811},"hosp_60_64":{"mean":1.0873,"sd":0.2119},"hosp_65_69":{"mean":0.6364,"sd":0.1324},"hosp_70_74":{"mean":0.3944,"sd":0.0876},"hosp_75_79":{"mean":0.2098,"sd":0.0497},"hosp_80_84":{"mean":0.0869,"sd":0.0219},"hosp_85_89":{"mean":0.0261,"sd":0.0069},"hosp_90_94":{"mean":0.0045,"sd":0.0013},"hosp_95_99":{"mean":0,"sd":0}},"TCD.16.1_1":{"FOI":{"mean":0.058,"sd":0.0082},"serop9":{"mean":40.5293,"sd":4.3385},"serop9_class":{"mean":40.5293,"sd":4.3385},"hosp_total":{"mean":154.8427,"sd":29.9797},"hosp_0_4":{"mean":25.5188,"sd":6.6701},"hosp_5_9":{"mean":27.3633,"sd":6.4451},"hosp_10_14":{"mean":25.142,"sd":5.3939},"hosp_15_19":{"mean":21.0076,"sd":4.1085},"hosp_20_24":{"mean":16.3686,"sd":2.9418},"hosp_25_29":{"mean":12.1142,"sd":2.0371},"hosp_30_34":{"mean":8.7225,"sd":1.4112},"hosp_35_39":{"mean":6.0792,"sd":0.9787},"hosp_40_44":{"mean":4.1452,"sd":0.6863},"hosp_45_49":{"mean":2.8003,"sd":0.4892},"hosp_50_54":{"mean":1.9855,"sd":0.372},"hosp_55_59":{"mean":1.4244,"sd":0.2885},"hosp_60_64":{"mean":0.986,"sd":0.2162},"hosp_65_69":{"mean":0.565,"sd":0.1339},"hosp_70_74":{"mean":0.3431,"sd":0.0875},"hosp_75_79":{"mean":0.179,"sd":0.0489},"hosp_80_84":{"mean":0.0728,"sd":0.0212},"hosp_85_89":{"mean":0.0215,"sd":0.0066},"hosp_90_94":{"mean":0.0037,"sd":0.0012},"hosp_95_99":{"mean":0,"sd":0}},"TCD.16.2_1":{"FOI":{"mean":0.0642,"sd":0.0067},"serop9":{"mean":43.7754,"sd":3.3555},"serop9_class":{"mean":43.7754,"sd":3.3555},"hosp_total":{"mean":167.9412,"sd":30.0443},"hosp_0_4":{"mean":28.7252,"sd":6.7093},"hosp_5_9":{"mean":30.8817,"sd":6.3455},"hosp_10_14":{"mean":28.0273,"sd":5.2965},"hosp_15_19":{"mean":23.0153,"sd":4.0592},"hosp_20_24":{"mean":17.5829,"sd":2.9405},"hosp_25_29":{"mean":12.7424,"sd":2.0623},"hosp_30_34":{"mean":8.9774,"sd":1.4398},"hosp_35_39":{"mean":6.1194,"sd":0.9957},"hosp_40_44":{"mean":4.0801,"sd":0.6873},"hosp_45_49":{"mean":2.695,"sd":0.4769},"hosp_50_54":{"mean":1.8685,"sd":0.3506},"hosp_55_59":{"mean":1.311,"sd":0.2619},"hosp_60_64":{"mean":0.888,"sd":0.189},"hosp_65_69":{"mean":0.4981,"sd":0.1128},"hosp_70_74":{"mean":0.2962,"sd":0.0711},"hosp_75_79":{"mean":0.1515,"sd":0.0384},"hosp_80_84":{"mean":0.0604,"sd":0.0161},"hosp_85_89":{"mean":0.0175,"sd":0.0049},"hosp_90_94":{"mean":0.0029,"sd":0.0009},"hosp_95_99":{"mean":0,"sd":0}},"TCD.16.3_1":{"FOI":{"mean":0.0572,"sd":0.0062},"serop9":{"mean":40.1472,"sd":3.2848},"serop9_class":{"mean":40.1472,"sd":3.2848},"hosp_total":{"mean":153.4636,"sd":27.6965},"hosp_0_4":{"mean":25.059,"sd":5.9289},"hosp_5_9":{"mean":26.8876,"sd":5.6157},"hosp_10_14":{"mean":24.7962,"sd":4.7709},"hosp_15_19":{"mean":20.8084,"sd":3.7364},"hosp_20_24":{"mean":16.2832,"sd":2.7639},"hosp_25_29":{"mean":12.0996,"sd":1.9738},"hosp_30_34":{"mean":8.744,"sd":1.3984},"hosp_35_39":{"mean":6.1138,"sd":0.9791},"hosp_40_44":{"mean":4.1805,"sd":0.6836},"hosp_45_49":{"mean":2.8307,"sd":0.4802},"hosp_50_54":{"mean":2.0108,"sd":0.3578},"hosp_55_59":{"mean":1.4447,"sd":0.2715},"hosp_60_64":{"mean":1.0011,"sd":0.1993},"hosp_65_69":{"mean":0.574,"sd":0.1211},"hosp_70_74":{"mean":0.3487,"sd":0.0778},"hosp_75_79":{"mean":0.1819,"sd":0.0429},"hosp_80_84":{"mean":0.0739,"sd":0.0183},"hosp_85_89":{"mean":0.0218,"sd":0.0057},"hosp_90_94":{"mean":0.0037,"sd":0.001},"hosp_95_99":{"mean":0,"sd":0}},"TCD.17.1_1":{"FOI":{"mean":0.0446,"sd":0.0049},"serop9":{"mean":32.9909,"sd":2.9289},"serop9_class":{"mean":32.9909,"sd":2.9289},"hosp_total":{"mean":124.1859,"sd":23.4569},"hosp_0_4":{"mean":18.7244,"sd":4.4859},"hosp_5_9":{"mean":19.8595,"sd":4.3124},"hosp_10_14":{"mean":18.7505,"sd":3.8256},"hosp_15_19":{"mean":16.3066,"sd":3.1458},"hosp_20_24":{"mean":13.2949,"sd":2.4331},"hosp_25_29":{"mean":10.3196,"sd":1.8002},"hosp_30_34":{"mean":7.7999,"sd":1.3064},"hosp_35_39":{"mean":5.707,"sd":0.9269},"hosp_40_44":{"mean":4.0837,"sd":0.6511},"hosp_45_49":{"mean":2.8929,"sd":0.4589},"hosp_50_54":{"mean":2.1489,"sd":0.3439},"hosp_55_59":{"mean":1.6133,"sd":0.2637},"hosp_60_64":{"mean":1.1672,"sd":0.197},"hosp_65_69":{"mean":0.6981,"sd":0.1227},"hosp_70_74":{"mean":0.4418,"sd":0.0813},"hosp_75_79":{"mean":0.2399,"sd":0.0464},"hosp_80_84":{"mean":0.1013,"sd":0.0206},"hosp_85_89":{"mean":0.031,"sd":0.0066},"hosp_90_94":{"mean":0.0055,"sd":0.0012},"hosp_95_99":{"mean":0,"sd":0}},"TCD.17.2_1":{"FOI":{"mean":0.0495,"sd":0.0059},"serop9":{"mean":35.853,"sd":3.3879},"serop9_class":{"mean":35.853,"sd":3.3879},"hosp_total":{"mean":136.0465,"sd":26.1843},"hosp_0_4":{"mean":21.1621,"sd":5.2664},"hosp_5_9":{"mean":22.5769,"sd":5.093},"hosp_10_14":{"mean":21.1332,"sd":4.4387},"hosp_15_19":{"mean":18.1272,"sd":3.5579},"hosp_20_24":{"mean":14.5437,"sd":2.6773},"hosp_25_29":{"mean":11.0968,"sd":1.9294},"hosp_30_34":{"mean":8.2404,"sd":1.3688},"hosp_35_39":{"mean":5.9224,"sd":0.9546},"hosp_40_44":{"mean":4.1627,"sd":0.6633},"hosp_45_49":{"mean":2.897,"sd":0.4653},"hosp_50_54":{"mean":2.1145,"sd":0.3485},"hosp_55_59":{"mean":1.5603,"sd":0.2678},"hosp_60_64":{"mean":1.11,"sd":0.2005},"hosp_65_69":{"mean":0.653,"sd":0.1249},"hosp_70_74":{"mean":0.4066,"sd":0.0826},"hosp_75_79":{"mean":0.2174,"sd":0.047},"hosp_80_84":{"mean":0.0904,"sd":0.0208},"hosp_85_89":{"mean":0.0273,"sd":0.0066},"hosp_90_94":{"mean":0.0048,"sd":0.0012},"hosp_95_99":{"mean":0,"sd":0}},"TCD.17.3_1":{"FOI":{"mean":0.0466,"sd":0.0055},"serop9":{"mean":34.1885,"sd":3.2653},"serop9_class":{"mean":34.1885,"sd":3.2653},"hosp_total":{"mean":129.1645,"sd":24.9364},"hosp_0_4":{"mean":19.7369,"sd":4.8892},"hosp_5_9":{"mean":20.9857,"sd":4.7225},"hosp_10_14":{"mean":19.742,"sd":4.1539},"hosp_15_19":{"mean":17.069,"sd":3.3722},"hosp_20_24":{"mean":13.8223,"sd":2.5716},"hosp_25_29":{"mean":10.6515,"sd":1.8764},"hosp_30_34":{"mean":7.991,"sd":1.3447},"hosp_35_39":{"mean":5.803,"sd":0.9446},"hosp_40_44":{"mean":4.1214,"sd":0.6589},"hosp_45_49":{"mean":2.898,"sd":0.4629},"hosp_50_54":{"mean":2.137,"sd":0.3467},"hosp_55_59":{"mean":1.5929,"sd":0.2663},"hosp_60_64":{"mean":1.1445,"sd":0.1995},"hosp_65_69":{"mean":0.6798,"sd":0.1245},"hosp_70_74":{"mean":0.4274,"sd":0.0827},"hosp_75_79":{"mean":0.2306,"sd":0.0472},"hosp_80_84":{"mean":0.0968,"sd":0.021},"hosp_85_89":{"mean":0.0294,"sd":0.0068},"hosp_90_94":{"mean":0.0052,"sd":0.0013},"hosp_95_99":{"mean":0,"sd":0}},"TCD.18.1_1":{"FOI":{"mean":0.0545,"sd":0.0063},"serop9":{"mean":38.6919,"sd":3.4045},"serop9_class":{"mean":38.6919,"sd":3.4045},"hosp_total":{"mean":147.5034,"sd":27.0013},"hosp_0_4":{"mean":23.6803,"sd":5.7043},"hosp_5_9":{"mean":25.3675,"sd":5.4392},"hosp_10_14":{"mean":23.5203,"sd":4.648},"hosp_15_19":{"mean":19.8906,"sd":3.6545},"hosp_20_24":{"mean":15.7018,"sd":2.7082},"hosp_25_29":{"mean":11.7763,"sd":1.9345},"hosp_30_34":{"mean":8.5918,"sd":1.3705},"hosp_35_39":{"mean":6.0657,"sd":0.9607},"hosp_40_44":{"mean":4.1879,"sd":0.6733},"hosp_45_49":{"mean":2.8632,"sd":0.4763},"hosp_50_54":{"mean":2.0535,"sd":0.3585},"hosp_55_59":{"mean":1.4893,"sd":0.2753},"hosp_60_64":{"mean":1.0416,"sd":0.2049},"hosp_65_69":{"mean":0.6027,"sd":0.1263},"hosp_70_74":{"mean":0.3693,"sd":0.0823},"hosp_75_79":{"mean":0.1943,"sd":0.046},"hosp_80_84":{"mean":0.0796,"sd":0.0199},"hosp_85_89":{"mean":0.0237,"sd":0.0062},"hosp_90_94":{"mean":0.0041,"sd":0.0011},"hosp_95_99":{"mean":0,"sd":0}},"TCD.18.2_1":{"FOI":{"mean":0.0543,"sd":0.0066},"serop9":{"mean":38.5533,"sd":3.6143},"serop9_class":{"mean":38.5533,"sd":3.6143},"hosp_total":{"mean":146.9563,"sd":27.3919},"hosp_0_4":{"mean":23.5705,"sd":5.7541},"hosp_5_9":{"mean":25.2486,"sd":5.5415},"hosp_10_14":{"mean":23.4149,"sd":4.7482},"hosp_15_19":{"mean":19.808,"sd":3.7302},"hosp_20_24":{"mean":15.6432,"sd":2.7554},"hosp_25_29":{"mean":11.7381,"sd":1.9585},"hosp_30_34":{"mean":8.5688,"sd":1.3798},"hosp_35_39":{"mean":6.0532,"sd":0.9625},"hosp_40_44":{"mean":4.1822,"sd":0.6726},"hosp_45_49":{"mean":2.8615,"sd":0.4755},"hosp_50_54":{"mean":2.0539,"sd":0.3585},"hosp_55_59":{"mean":1.4909,"sd":0.2763},"hosp_60_64":{"mean":1.0437,"sd":0.2066},"hosp_65_69":{"mean":0.6045,"sd":0.128},"hosp_70_74":{"mean":0.3708,"sd":0.0839},"hosp_75_79":{"mean":0.1953,"sd":0.0471},"hosp_80_84":{"mean":0.0801,"sd":0.0205},"hosp_85_89":{"mean":0.0238,"sd":0.0065},"hosp_90_94":{"mean":0.0041,"sd":0.0012},"hosp_95_99":{"mean":0,"sd":0}},"TCD.18.3_1":{"FOI":{"mean":0.0576,"sd":0.006},"serop9":{"mean":40.3835,"sd":3.1863},"serop9_class":{"mean":40.3835,"sd":3.1863},"hosp_total":{"mean":154.4258,"sd":27.6122},"hosp_0_4":{"mean":25.2751,"sd":5.8974},"hosp_5_9":{"mean":27.1338,"sd":5.5915},"hosp_10_14":{"mean":25.0048,"sd":4.7523},"hosp_15_19":{"mean":20.959,"sd":3.7223},"hosp_20_24":{"mean":16.3786,"sd":2.7541},"hosp_25_29":{"mean":12.1526,"sd":1.9677},"hosp_30_34":{"mean":8.7687,"sd":1.3948},"hosp_35_39":{"mean":6.1214,"sd":0.9769},"hosp_40_44":{"mean":4.179,"sd":0.682},"hosp_45_49":{"mean":2.8251,"sd":0.4788},"hosp_50_54":{"mean":2.0036,"sd":0.3564},"hosp_55_59":{"mean":1.4372,"sd":0.27},"hosp_60_64":{"mean":0.9943,"sd":0.1979},"hosp_65_69":{"mean":0.5693,"sd":0.12},"hosp_70_74":{"mean":0.3452,"sd":0.077},"hosp_75_79":{"mean":0.1799,"sd":0.0423},"hosp_80_84":{"mean":0.073,"sd":0.0181},"hosp_85_89":{"mean":0.0215,"sd":0.0056},"hosp_90_94":{"mean":0.0037,"sd":0.001},"hosp_95_99":{"mean":0,"sd":0}},"TCD.19.1_1":{"FOI":{"mean":0.05,"sd":0.0058},"serop9":{"mean":36.1638,"sd":3.3249},"serop9_class":{"mean":36.1638,"sd":3.3249},"hosp_total":{"mean":137.3083,"sd":26.0696},"hosp_0_4":{"mean":21.4234,"sd":5.2618},"hosp_5_9":{"mean":22.867,"sd":5.0702},"hosp_10_14":{"mean":21.3865,"sd":4.4116},"hosp_15_19":{"mean":18.3201,"sd":3.5346},"hosp_20_24":{"mean":14.6756,"sd":2.6615},"hosp_25_29":{"mean":11.1788,"sd":1.9215},"hosp_30_34":{"mean":8.2867,"sd":1.3668},"hosp_35_39":{"mean":5.945,"sd":0.9561},"hosp_40_44":{"mean":4.171,"sd":0.6661},"hosp_45_49":{"mean":2.8974,"sd":0.468},"hosp_50_54":{"mean":2.1109,"sd":0.3507},"hosp_55_59":{"mean":1.5548,"sd":0.2691},"hosp_60_64":{"mean":1.104,"sd":0.2009},"hosp_65_69":{"mean":0.6483,"sd":0.1247},"hosp_70_74":{"mean":0.403,"sd":0.0822},"hosp_75_79":{"mean":0.215,"sd":0.0465},"hosp_80_84":{"mean":0.0893,"sd":0.0204},"hosp_85_89":{"mean":0.0269,"sd":0.0065},"hosp_90_94":{"mean":0.0047,"sd":0.0012},"hosp_95_99":{"mean":0,"sd":0}},"TCD.19.2_1":{"FOI":{"mean":0.0506,"sd":0.0057},"serop9":{"mean":36.5234,"sd":3.2594},"serop9_class":{"mean":36.5234,"sd":3.2594},"hosp_total":{"mean":138.7509,"sd":25.8491},"hosp_0_4":{"mean":21.7228,"sd":5.2307},"hosp_5_9":{"mean":23.2045,"sd":5.0227},"hosp_10_14":{"mean":21.6817,"sd":4.3665},"hosp_15_19":{"mean":18.5437,"sd":3.4987},"hosp_20_24":{"mean":14.827,"sd":2.6364},"hosp_25_29":{"mean":11.2711,"sd":1.9061},"hosp_30_34":{"mean":8.3374,"sd":1.3586},"hosp_35_39":{"mean":5.9684,"sd":0.9528},"hosp_40_44":{"mean":4.1781,"sd":0.6655},"hosp_45_49":{"mean":2.8959,"sd":0.4687},"hosp_50_54":{"mean":2.1051,"sd":0.3517},"hosp_55_59":{"mean":1.5471,"sd":0.27},"hosp_60_64":{"mean":1.0962,"sd":0.2016},"hosp_65_69":{"mean":0.6423,"sd":0.125},"hosp_70_74":{"mean":0.3984,"sd":0.0823},"hosp_75_79":{"mean":0.2122,"sd":0.0465},"hosp_80_84":{"mean":0.0879,"sd":0.0204},"hosp_85_89":{"mean":0.0264,"sd":0.0065},"hosp_90_94":{"mean":0.0046,"sd":0.0012},"hosp_95_99":{"mean":0,"sd":0}},"TCD.2.1_1":{"FOI":{"mean":0.0466,"sd":0.0063},"serop9":{"mean":34.1707,"sd":3.7291},"serop9_class":{"mean":34.1707,"sd":3.7291},"hosp_total":{"mean":128.988,"sd":25.8653},"hosp_0_4":{"mean":19.7466,"sd":5.1316},"hosp_5_9":{"mean":20.9863,"sd":4.9926},"hosp_10_14":{"mean":19.7279,"sd":4.3765},"hosp_15_19":{"mean":17.0441,"sd":3.527},"hosp_20_24":{"mean":13.7928,"sd":2.6646},"hosp_25_29":{"mean":10.6228,"sd":1.924},"hosp_30_34":{"mean":7.966,"sd":1.3646},"hosp_35_39":{"mean":5.7831,"sd":0.9499},"hosp_40_44":{"mean":4.1065,"sd":0.6586},"hosp_45_49":{"mean":2.8875,"sd":0.4616},"hosp_50_54":{"mean":2.1295,"sd":0.3464},"hosp_55_59":{"mean":1.5876,"sd":0.2676},"hosp_60_64":{"mean":1.1411,"sd":0.2021},"hosp_65_69":{"mean":0.6781,"sd":0.1274},"hosp_70_74":{"mean":0.4266,"sd":0.0854},"hosp_75_79":{"mean":0.2303,"sd":0.0493},"hosp_80_84":{"mean":0.0967,"sd":0.0221},"hosp_85_89":{"mean":0.0294,"sd":0.0072},"hosp_90_94":{"mean":0.0052,"sd":0.0013},"hosp_95_99":{"mean":0,"sd":0}},"TCD.2.2_1":{"FOI":{"mean":0.0469,"sd":0.0066},"serop9":{"mean":34.3145,"sd":3.885},"serop9_class":{"mean":34.3145,"sd":3.885},"hosp_total":{"mean":129.5839,"sd":26.3939},"hosp_0_4":{"mean":19.8797,"sd":5.2521},"hosp_5_9":{"mean":21.1357,"sd":5.1455},"hosp_10_14":{"mean":19.8553,"sd":4.5065},"hosp_15_19":{"mean":17.1371,"sd":3.6172},"hosp_20_24":{"mean":13.8527,"sd":2.7175},"hosp_25_29":{"mean":10.6568,"sd":1.9497},"hosp_30_34":{"mean":7.9825,"sd":1.3739},"hosp_35_39":{"mean":5.7888,"sd":0.9509},"hosp_40_44":{"mean":4.1063,"sd":0.6566},"hosp_45_49":{"mean":2.8845,"sd":0.4594},"hosp_50_54":{"mean":2.1253,"sd":0.3449},"hosp_55_59":{"mean":1.5832,"sd":0.2671},"hosp_60_64":{"mean":1.137,"sd":0.2024},"hosp_65_69":{"mean":0.6752,"sd":0.1281},"hosp_70_74":{"mean":0.4244,"sd":0.0862},"hosp_75_79":{"mean":0.229,"sd":0.0499},"hosp_80_84":{"mean":0.0962,"sd":0.0224},"hosp_85_89":{"mean":0.0293,"sd":0.0073},"hosp_90_94":{"mean":0.0052,"sd":0.0014},"hosp_95_99":{"mean":0,"sd":0}},"TCD.2.3_1":{"FOI":{"mean":0.0305,"sd":0.0066},"serop9":{"mean":23.8623,"sd":4.5461},"serop9_class":{"mean":23.8623,"sd":4.5461},"hosp_total":{"mean":85.7889,"sd":24.782},"hosp_0_4":{"mean":12.2,"sd":4.1398},"hosp_5_9":{"mean":12.535,"sd":4.2021},"hosp_10_14":{"mean":11.9508,"sd":3.8883},"hosp_15_19":{"mean":10.6751,"sd":3.3258},"hosp_20_24":{"mean":9.0172,"sd":2.6651},"hosp_25_29":{"mean":7.2876,"sd":2.0296},"hosp_30_34":{"mean":5.7529,"sd":1.5022},"hosp_35_39":{"mean":4.4051,"sd":1.0746},"hosp_40_44":{"mean":3.3033,"sd":0.7512},"hosp_45_49":{"mean":2.4546,"sd":0.5201},"hosp_50_54":{"mean":1.9137,"sd":0.3785},"hosp_55_59":{"mean":1.5086,"sd":0.2798},"hosp_60_64":{"mean":1.1463,"sd":0.2011},"hosp_65_69":{"mean":0.72,"sd":0.121},"hosp_70_74":{"mean":0.4785,"sd":0.0783},"hosp_75_79":{"mean":0.2728,"sd":0.0443},"hosp_80_84":{"mean":0.121,"sd":0.0199},"hosp_85_89":{"mean":0.0388,"sd":0.0066},"hosp_90_94":{"mean":0.0072,"sd":0.0013},"hosp_95_99":{"mean":0,"sd":0}},"TCD.20.1_1":{"FOI":{"mean":0.0506,"sd":0.0077},"serop9":{"mean":36.4084,"sd":4.349},"serop9_class":{"mean":36.4084,"sd":4.349},"hosp_total":{"mean":138.043,"sd":27.8144},"hosp_0_4":{"mean":21.6909,"sd":5.7972},"hosp_5_9":{"mean":23.145,"sd":5.6799},"hosp_10_14":{"mean":21.5887,"sd":4.8929},"hosp_15_19":{"mean":18.434,"sd":3.8404},"hosp_20_24":{"mean":14.7195,"sd":2.819},"hosp_25_29":{"mean":11.1786,"sd":1.9821},"hosp_30_34":{"mean":8.2643,"sd":1.3783},"hosp_35_39":{"mean":5.9151,"sd":0.9508},"hosp_40_44":{"mean":4.1418,"sd":0.6613},"hosp_45_49":{"mean":2.8726,"sd":0.4697},"hosp_50_54":{"mean":2.0903,"sd":0.3589},"hosp_55_59":{"mean":1.5383,"sd":0.2821},"hosp_60_64":{"mean":1.0918,"sd":0.2159},"hosp_65_69":{"mean":0.641,"sd":0.1372},"hosp_70_74":{"mean":0.3985,"sd":0.0922},"hosp_75_79":{"mean":0.2128,"sd":0.0531},"hosp_80_84":{"mean":0.0884,"sd":0.0237},"hosp_85_89":{"mean":0.0266,"sd":0.0076},"hosp_90_94":{"mean":0.0047,"sd":0.0014},"hosp_95_99":{"mean":0,"sd":0}},"TCD.20.2_1":{"FOI":{"mean":0.0522,"sd":0.006},"serop9":{"mean":37.4114,"sd":3.3517},"serop9_class":{"mean":37.4114,"sd":3.3517},"hosp_total":{"mean":142.3104,"sd":26.1253},"hosp_0_4":{"mean":22.508,"sd":5.4092},"hosp_5_9":{"mean":24.0709,"sd":5.1483},"hosp_10_14":{"mean":22.422,"sd":4.4368},"hosp_15_19":{"mean":19.0905,"sd":3.5285},"hosp_20_24":{"mean":15.1863,"sd":2.6445},"hosp_25_29":{"mean":11.482,"sd":1.9067},"hosp_30_34":{"mean":8.4466,"sd":1.3594},"hosp_35_39":{"mean":6.013,"sd":0.956},"hosp_40_44":{"mean":4.1861,"sd":0.6707},"hosp_45_49":{"mean":2.8856,"sd":0.4744},"hosp_50_54":{"mean":2.0863,"sd":0.3571},"hosp_55_59":{"mean":1.5252,"sd":0.2746},"hosp_60_64":{"mean":1.075,"sd":0.2049},"hosp_65_69":{"mean":0.6267,"sd":0.1268},"hosp_70_74":{"mean":0.3868,"sd":0.0831},"hosp_75_79":{"mean":0.205,"sd":0.0467},"hosp_80_84":{"mean":0.0846,"sd":0.0204},"hosp_85_89":{"mean":0.0253,"sd":0.0064},"hosp_90_94":{"mean":0.0044,"sd":0.0012},"hosp_95_99":{"mean":0,"sd":0}},"TCD.20.3_1":{"FOI":{"mean":0.0498,"sd":0.0069},"serop9":{"mean":35.9945,"sd":3.9648},"serop9_class":{"mean":35.9945,"sd":3.9648},"hosp_total":{"mean":136.3991,"sd":26.6802},"hosp_0_4":{"mean":21.2952,"sd":5.4635},"hosp_5_9":{"mean":22.7135,"sd":5.312},"hosp_10_14":{"mean":21.2318,"sd":4.6047},"hosp_15_19":{"mean":18.182,"sd":3.6554},"hosp_20_24":{"mean":14.5639,"sd":2.7194},"hosp_25_29":{"mean":11.0954,"sd":1.9384},"hosp_30_34":{"mean":8.2281,"sd":1.3637},"hosp_35_39":{"mean":5.9066,"sd":0.9478},"hosp_40_44":{"mean":4.1474,"sd":0.6605},"hosp_45_49":{"mean":2.8841,"sd":0.4675},"hosp_50_54":{"mean":2.1038,"sd":0.3548},"hosp_55_59":{"mean":1.5518,"sd":0.2768},"hosp_60_64":{"mean":1.1037,"sd":0.2103},"hosp_65_69":{"mean":0.6493,"sd":0.1329},"hosp_70_74":{"mean":0.4044,"sd":0.089},"hosp_75_79":{"mean":0.2162,"sd":0.0511},"hosp_80_84":{"mean":0.09,"sd":0.0228},"hosp_85_89":{"mean":0.0272,"sd":0.0073},"hosp_90_94":{"mean":0.0047,"sd":0.0014},"hosp_95_99":{"mean":0,"sd":0}},"TCD.21.1_1":{"FOI":{"mean":4.82e-07,"sd":5.77e-06},"serop9":{"mean":0.0004,"sd":0.0052},"serop9_class":{"mean":0.0004,"sd":0.0052},"hosp_total":{"mean":0.0008,"sd":0.0096},"hosp_0_4":{"mean":0.0001,"sd":0.0017},"hosp_5_9":{"mean":0.0001,"sd":0.0015},"hosp_10_14":{"mean":0.0001,"sd":0.0013},"hosp_15_19":{"mean":0.0001,"sd":0.0011},"hosp_20_24":{"mean":0.0001,"sd":0.0009},"hosp_25_29":{"mean":0.0001,"sd":0.0007},"hosp_30_34":{"mean":0,"sd":0.0006},"hosp_35_39":{"mean":0,"sd":0.0005},"hosp_40_44":{"mean":0,"sd":0.0004},"hosp_45_49":{"mean":0,"sd":0.0003},"hosp_50_54":{"mean":0,"sd":0.0002},"hosp_55_59":{"mean":0,"sd":0.0002},"hosp_60_64":{"mean":0,"sd":0.0002},"hosp_65_69":{"mean":8.9e-06,"sd":0.0001},"hosp_70_74":{"mean":6.37e-06,"sd":0.0001},"hosp_75_79":{"mean":3.91e-06,"sd":0},"hosp_80_84":{"mean":1.88e-06,"sd":0},"hosp_85_89":{"mean":6.52e-07,"sd":7.68e-06},"hosp_90_94":{"mean":1.31e-07,"sd":1.55e-06},"hosp_95_99":{"mean":0,"sd":0}},"TCD.22.1_1":{"FOI":{"mean":0.0494,"sd":0.0082},"serop9":{"mean":35.7382,"sd":4.6926},"serop9_class":{"mean":35.7382,"sd":4.6926},"hosp_total":{"mean":135.2287,"sd":27.9899},"hosp_0_4":{"mean":21.1114,"sd":5.6973},"hosp_5_9":{"mean":22.5078,"sd":5.6445},"hosp_10_14":{"mean":21.0318,"sd":4.9091},"hosp_15_19":{"mean":18.0079,"sd":3.8878},"hosp_20_24":{"mean":14.4256,"sd":2.8767},"hosp_25_29":{"mean":10.9936,"sd":2.0352},"hosp_30_34":{"mean":8.1573,"sd":1.4195},"hosp_35_39":{"mean":5.8606,"sd":0.9782},"hosp_40_44":{"mean":4.1196,"sd":0.6771},"hosp_45_49":{"mean":2.8684,"sd":0.4776},"hosp_50_54":{"mean":2.0956,"sd":0.3626},"hosp_55_59":{"mean":1.5484,"sd":0.2838},"hosp_60_64":{"mean":1.1034,"sd":0.2169},"hosp_65_69":{"mean":0.6505,"sd":0.1379},"hosp_70_74":{"mean":0.4061,"sd":0.093},"hosp_75_79":{"mean":0.2177,"sd":0.0538},"hosp_80_84":{"mean":0.0908,"sd":0.0242},"hosp_85_89":{"mean":0.0275,"sd":0.0078},"hosp_90_94":{"mean":0.0048,"sd":0.0015},"hosp_95_99":{"mean":0,"sd":0}},"TCD.23.1_1":{"FOI":{"mean":0.0361,"sd":0.0054},"serop9":{"mean":27.6295,"sd":3.4738},"serop9_class":{"mean":27.6295,"sd":3.4738},"hosp_total":{"mean":101.663,"sd":22.6075},"hosp_0_4":{"mean":14.6916,"sd":4.047},"hosp_5_9":{"mean":15.3267,"sd":4.0067},"hosp_10_14":{"mean":14.5984,"sd":3.6333},"hosp_15_19":{"mean":12.9364,"sd":3.0463},"hosp_20_24":{"mean":10.8004,"sd":2.3944},"hosp_25_29":{"mean":8.6083,"sd":1.792},"hosp_30_34":{"mean":6.6921,"sd":1.3079},"hosp_35_39":{"mean":5.0413,"sd":0.9274},"hosp_40_44":{"mean":3.7165,"sd":0.6472},"hosp_45_49":{"mean":2.7135,"sd":0.4515},"hosp_50_54":{"mean":2.0778,"sd":0.3345},"hosp_55_59":{"mean":1.6082,"sd":0.2544},"hosp_60_64":{"mean":1.1995,"sd":0.1895},"hosp_65_69":{"mean":0.7394,"sd":0.1186},"hosp_70_74":{"mean":0.4822,"sd":0.0796},"hosp_75_79":{"mean":0.2697,"sd":0.0464},"hosp_80_84":{"mean":0.1173,"sd":0.0212},"hosp_85_89":{"mean":0.0369,"sd":0.007},"hosp_90_94":{"mean":0.0067,"sd":0.0014},"hosp_95_99":{"mean":0,"sd":0}},"TCD.23.2_1":{"FOI":{"mean":0.028,"sd":0.0065},"serop9":{"mean":22.1242,"sd":4.5546},"serop9_class":{"mean":22.1242,"sd":4.5546},"hosp_total":{"mean":78.4994,"sd":23.8208},"hosp_0_4":{"mean":11.0744,"sd":3.8314},"hosp_5_9":{"mean":11.2934,"sd":3.8958},"hosp_10_14":{"mean":10.771,"sd":3.6425},"hosp_15_19":{"mean":9.6585,"sd":3.1584},"hosp_20_24":{"mean":8.205,"sd":2.5694},"hosp_25_29":{"mean":6.6759,"sd":1.9877},"hosp_30_34":{"mean":5.309,"sd":1.4945},"hosp_35_39":{"mean":4.0969,"sd":1.0856},"hosp_40_44":{"mean":3.0969,"sd":0.7698},"hosp_45_49":{"mean":2.3201,"sd":0.5398},"hosp_50_54":{"mean":1.8239,"sd":0.3967},"hosp_55_59":{"mean":1.4497,"sd":0.2951},"hosp_60_64":{"mean":1.1108,"sd":0.2123},"hosp_65_69":{"mean":0.7036,"sd":0.127},"hosp_70_74":{"mean":0.4715,"sd":0.0813},"hosp_75_79":{"mean":0.2711,"sd":0.0452},"hosp_80_84":{"mean":0.1212,"sd":0.0199},"hosp_85_89":{"mean":0.0392,"sd":0.0065},"hosp_90_94":{"mean":0.0073,"sd":0.0012},"hosp_95_99":{"mean":0,"sd":0}},"TCD.23.3_1":{"FOI":{"mean":0.0074,"sd":0.0048},"serop9":{"mean":6.3785,"sd":3.9967},"serop9_class":{"mean":6.3785,"sd":3.9967},"hosp_total":{"mean":18.3559,"sd":14.4092},"hosp_0_4":{"mean":2.7249,"sd":2.0497},"hosp_5_9":{"mean":2.5138,"sd":1.9539},"hosp_10_14":{"mean":2.3072,"sd":1.8305},"hosp_15_19":{"mean":2.0587,"sd":1.6527},"hosp_20_24":{"mean":1.7759,"sd":1.4334},"hosp_25_29":{"mean":1.4866,"sd":1.2009},"hosp_30_34":{"mean":1.2272,"sd":0.9886},"hosp_35_39":{"mean":0.9893,"sd":0.7926},"hosp_40_44":{"mean":0.7847,"sd":0.624},"hosp_45_49":{"mean":0.619,"sd":0.4877},"hosp_50_54":{"mean":0.5136,"sd":0.4004},"hosp_55_59":{"mean":0.4318,"sd":0.3326},"hosp_60_64":{"mean":0.3503,"sd":0.2665},"hosp_65_69":{"mean":0.2352,"sd":0.1765},"hosp_70_74":{"mean":0.1672,"sd":0.1237},"hosp_75_79":{"mean":0.102,"sd":0.0744},"hosp_80_84":{"mean":0.0484,"sd":0.0348},"hosp_85_89":{"mean":0.0166,"sd":0.0118},"hosp_90_94":{"mean":0.0033,"sd":0.0023},"hosp_95_99":{"mean":0,"sd":0}},"TCD.3.1_1":{"FOI":{"mean":0.0001,"sd":0.0001},"serop9":{"mean":0.0938,"sd":0.084},"serop9_class":{"mean":0.0938,"sd":0.084},"hosp_total":{"mean":0.2016,"sd":0.2007},"hosp_0_4":{"mean":0.0366,"sd":0.0366},"hosp_5_9":{"mean":0.0309,"sd":0.0308},"hosp_10_14":{"mean":0.0264,"sd":0.0263},"hosp_15_19":{"mean":0.0223,"sd":0.0222},"hosp_20_24":{"mean":0.0184,"sd":0.0183},"hosp_25_29":{"mean":0.0149,"sd":0.0148},"hosp_30_34":{"mean":0.012,"sd":0.0119},"hosp_35_39":{"mean":0.0095,"sd":0.0094},"hosp_40_44":{"mean":0.0074,"sd":0.0073},"hosp_45_49":{"mean":0.0058,"sd":0.0057},"hosp_50_54":{"mean":0.0048,"sd":0.0047},"hosp_55_59":{"mean":0.004,"sd":0.004},"hosp_60_64":{"mean":0.0032,"sd":0.0032},"hosp_65_69":{"mean":0.0022,"sd":0.0022},"hosp_70_74":{"mean":0.0016,"sd":0.0015},"hosp_75_79":{"mean":0.001,"sd":0.0009},"hosp_80_84":{"mean":0.0005,"sd":0.0005},"hosp_85_89":{"mean":0.0002,"sd":0.0002},"hosp_90_94":{"mean":0,"sd":0},"hosp_95_99":{"mean":0,"sd":0}},"TCD.4.1_1":{"FOI":{"mean":0.0488,"sd":0.0059},"serop9":{"mean":35.4678,"sd":3.4098},"serop9_class":{"mean":35.4678,"sd":3.4098},"hosp_total":{"mean":134.3246,"sd":25.2613},"hosp_0_4":{"mean":20.8047,"sd":5.075},"hosp_5_9":{"mean":22.1739,"sd":4.8749},"hosp_10_14":{"mean":20.781,"sd":4.2499},"hosp_15_19":{"mean":17.8605,"sd":3.4185},"hosp_20_24":{"mean":14.3632,"sd":2.5865},"hosp_25_29":{"mean":10.9867,"sd":1.8772},"hosp_30_34":{"mean":8.1798,"sd":1.3428},"hosp_35_39":{"mean":5.8944,"sd":0.9448},"hosp_40_44":{"mean":4.154,"sd":0.6621},"hosp_45_49":{"mean":2.8986,"sd":0.468},"hosp_50_54":{"mean":2.1213,"sd":0.3527},"hosp_55_59":{"mean":1.5694,"sd":0.2722},"hosp_60_64":{"mean":1.1193,"sd":0.2044},"hosp_65_69":{"mean":0.6601,"sd":0.1276},"hosp_70_74":{"mean":0.4121,"sd":0.0845},"hosp_75_79":{"mean":0.2208,"sd":0.0481},"hosp_80_84":{"mean":0.0921,"sd":0.0213},"hosp_85_89":{"mean":0.0278,"sd":0.0068},"hosp_90_94":{"mean":0.0049,"sd":0.0013},"hosp_95_99":{"mean":0,"sd":0}},"TCD.4.2_1":{"FOI":{"mean":0.0504,"sd":0.0071},"serop9":{"mean":36.3449,"sd":4.018},"serop9_class":{"mean":36.3449,"sd":4.018},"hosp_total":{"mean":137.8201,"sd":26.8715},"hosp_0_4":{"mean":21.6071,"sd":5.6013},"hosp_5_9":{"mean":23.054,"sd":5.4226},"hosp_10_14":{"mean":21.5221,"sd":4.6669},"hosp_15_19":{"mean":18.397,"sd":3.6783},"hosp_20_24":{"mean":14.7063,"sd":2.7205},"hosp_25_29":{"mean":11.1805,"sd":1.9324},"hosp_30_34":{"mean":8.2737,"sd":1.359},"hosp_35_39":{"mean":5.9269,"sd":0.9472},"hosp_40_44":{"mean":4.1531,"sd":0.6634},"hosp_45_49":{"mean":2.8821,"sd":0.4722},"hosp_50_54":{"mean":2.0982,"sd":0.3599},"hosp_55_59":{"mean":1.5447,"sd":0.2814},"hosp_60_64":{"mean":1.0965,"sd":0.2138},"hosp_65_69":{"mean":0.6438,"sd":0.1348},"hosp_70_74":{"mean":0.4003,"sd":0.0899},"hosp_75_79":{"mean":0.2136,"sd":0.0514},"hosp_80_84":{"mean":0.0888,"sd":0.0228},"hosp_85_89":{"mean":0.0267,"sd":0.0073},"hosp_90_94":{"mean":0.0047,"sd":0.0013},"hosp_95_99":{"mean":0,"sd":0}},"TCD.4.3_1":{"FOI":{"mean":0.0497,"sd":0.0067},"serop9":{"mean":35.9618,"sd":3.8655},"serop9_class":{"mean":35.9618,"sd":3.8655},"hosp_total":{"mean":136.379,"sd":27.0834},"hosp_0_4":{"mean":21.2835,"sd":5.513},"hosp_5_9":{"mean":22.6992,"sd":5.369},"hosp_10_14":{"mean":21.2226,"sd":4.662},"hosp_15_19":{"mean":18.1787,"sd":3.7087},"hosp_20_24":{"mean":14.5649,"sd":2.7638},"hosp_25_29":{"mean":11.0984,"sd":1.9708},"hosp_30_34":{"mean":8.2317,"sd":1.384},"hosp_35_39":{"mean":5.9098,"sd":0.9573},"hosp_40_44":{"mean":4.15,"sd":0.6622},"hosp_45_49":{"mean":2.886,"sd":0.4645},"hosp_50_54":{"mean":2.1052,"sd":0.3495},"hosp_55_59":{"mean":1.5527,"sd":0.2706},"hosp_60_64":{"mean":1.1042,"sd":0.2045},"hosp_65_69":{"mean":0.6495,"sd":0.1287},"hosp_70_74":{"mean":0.4045,"sd":0.0861},"hosp_75_79":{"mean":0.2162,"sd":0.0494},"hosp_80_84":{"mean":0.09,"sd":0.022},"hosp_85_89":{"mean":0.0271,"sd":0.0071},"hosp_90_94":{"mean":0.0047,"sd":0.0013},"hosp_95_99":{"mean":0,"sd":0}},"TCD.5.1_1":{"FOI":{"mean":0.0002,"sd":0.0002},"serop9":{"mean":0.1499,"sd":0.1869},"serop9_class":{"mean":0.1499,"sd":0.1869},"hosp_total":{"mean":0.3261,"sd":0.4706},"hosp_0_4":{"mean":0.059,"sd":0.0846},"hosp_5_9":{"mean":0.0498,"sd":0.0716},"hosp_10_14":{"mean":0.0427,"sd":0.0614},"hosp_15_19":{"mean":0.0361,"sd":0.052},"hosp_20_24":{"mean":0.0298,"sd":0.0431},"hosp_25_29":{"mean":0.0242,"sd":0.0349},"hosp_30_34":{"mean":0.0194,"sd":0.0282},"hosp_35_39":{"mean":0.0154,"sd":0.0223},"hosp_40_44":{"mean":0.012,"sd":0.0175},"hosp_45_49":{"mean":0.0094,"sd":0.0137},"hosp_50_54":{"mean":0.0077,"sd":0.0113},"hosp_55_59":{"mean":0.0065,"sd":0.0095},"hosp_60_64":{"mean":0.0053,"sd":0.0077},"hosp_65_69":{"mean":0.0036,"sd":0.0052},"hosp_70_74":{"mean":0.0025,"sd":0.0037},"hosp_75_79":{"mean":0.0016,"sd":0.0023},"hosp_80_84":{"mean":0.0007,"sd":0.0011},"hosp_85_89":{"mean":0.0003,"sd":0.0004},"hosp_90_94":{"mean":0.0001,"sd":0.0001},"hosp_95_99":{"mean":0,"sd":0}},"TCD.6.1_1":{"FOI":{"mean":0.001,"sd":0.001},"serop9":{"mean":0.8651,"sd":0.8863},"serop9_class":{"mean":0.8651,"sd":0.8863},"hosp_total":{"mean":1.9714,"sd":2.3178},"hosp_0_4":{"mean":0.3425,"sd":0.3903},"hosp_5_9":{"mean":0.293,"sd":0.3376},"hosp_10_14":{"mean":0.2541,"sd":0.2956},"hosp_15_19":{"mean":0.2173,"sd":0.255},"hosp_20_24":{"mean":0.1815,"sd":0.2147},"hosp_25_29":{"mean":0.1484,"sd":0.1768},"hosp_30_34":{"mean":0.1205,"sd":0.1445},"hosp_35_39":{"mean":0.0961,"sd":0.1159},"hosp_40_44":{"mean":0.0758,"sd":0.0918},"hosp_45_49":{"mean":0.0596,"sd":0.0726},"hosp_50_54":{"mean":0.0495,"sd":0.0605},"hosp_55_59":{"mean":0.0418,"sd":0.0512},"hosp_60_64":{"mean":0.0341,"sd":0.042},"hosp_65_69":{"mean":0.0231,"sd":0.0285},"hosp_70_74":{"mean":0.0166,"sd":0.0205},"hosp_75_79":{"mean":0.0103,"sd":0.0127},"hosp_80_84":{"mean":0.0049,"sd":0.0061},"hosp_85_89":{"mean":0.0017,"sd":0.0021},"hosp_90_94":{"mean":0.0003,"sd":0.0004},"hosp_95_99":{"mean":0,"sd":0}},"TCD.7.1_1":{"FOI":{"mean":0.0529,"sd":0.0071},"serop9":{"mean":37.7614,"sd":3.942},"serop9_class":{"mean":37.7614,"sd":3.942},"hosp_total":{"mean":143.642,"sd":27.6927},"hosp_0_4":{"mean":22.8685,"sd":5.8535},"hosp_5_9":{"mean":24.4576,"sd":5.6699},"hosp_10_14":{"mean":22.7286,"sd":4.8497},"hosp_15_19":{"mean":19.2936,"sd":3.7918},"hosp_20_24":{"mean":15.2998,"sd":2.7827},"hosp_25_29":{"mean":11.5325,"sd":1.964},"hosp_30_34":{"mean":8.4591,"sd":1.3752},"hosp_35_39":{"mean":6.0056,"sd":0.9561},"hosp_40_44":{"mean":4.1705,"sd":0.6685},"hosp_45_49":{"mean":2.8684,"sd":0.4748},"hosp_50_54":{"mean":2.0697,"sd":0.3607},"hosp_55_59":{"mean":1.5103,"sd":0.2806},"hosp_60_64":{"mean":1.0629,"sd":0.2119},"hosp_65_69":{"mean":0.6188,"sd":0.1326},"hosp_70_74":{"mean":0.3815,"sd":0.0878},"hosp_75_79":{"mean":0.202,"sd":0.0498},"hosp_80_84":{"mean":0.0833,"sd":0.0219},"hosp_85_89":{"mean":0.0249,"sd":0.0069},"hosp_90_94":{"mean":0.0043,"sd":0.0013},"hosp_95_99":{"mean":0,"sd":0}},"TCD.7.2_1":{"FOI":{"mean":0.0527,"sd":0.0078},"serop9":{"mean":37.6416,"sd":4.3273},"serop9_class":{"mean":37.6416,"sd":4.3273},"hosp_total":{"mean":143.121,"sd":28.5179},"hosp_0_4":{"mean":22.7967,"sd":6.0537},"hosp_5_9":{"mean":24.3694,"sd":5.9138},"hosp_10_14":{"mean":22.6379,"sd":5.0531},"hosp_15_19":{"mean":19.2121,"sd":3.9317},"hosp_20_24":{"mean":15.234,"sd":2.8651},"hosp_25_29":{"mean":11.4838,"sd":2.0056},"hosp_30_34":{"mean":8.4255,"sd":1.3934},"hosp_35_39":{"mean":5.9841,"sd":0.9631},"hosp_40_44":{"mean":4.1579,"sd":0.6718},"hosp_45_49":{"mean":2.8617,"sd":0.4778},"hosp_50_54":{"mean":2.0666,"sd":0.3645},"hosp_55_59":{"mean":1.5094,"sd":0.2852},"hosp_60_64":{"mean":1.0634,"sd":0.2167},"hosp_65_69":{"mean":0.6199,"sd":0.1364},"hosp_70_74":{"mean":0.3827,"sd":0.0908},"hosp_75_79":{"mean":0.2029,"sd":0.0517},"hosp_80_84":{"mean":0.0838,"sd":0.0228},"hosp_85_89":{"mean":0.0251,"sd":0.0073},"hosp_90_94":{"mean":0.0044,"sd":0.0013},"hosp_95_99":{"mean":0,"sd":0}},"TCD.7.3_1":{"FOI":{"mean":0.0604,"sd":0.0065},"serop9":{"mean":41.8453,"sd":3.3045},"serop9_class":{"mean":41.8453,"sd":3.3045},"hosp_total":{"mean":160.1933,"sd":28.5233},"hosp_0_4":{"mean":26.7073,"sd":6.243},"hosp_5_9":{"mean":28.7,"sd":5.9326},"hosp_10_14":{"mean":26.282,"sd":4.9876},"hosp_15_19":{"mean":21.8411,"sd":3.8515},"hosp_20_24":{"mean":16.9065,"sd":2.8118},"hosp_25_29":{"mean":12.4209,"sd":1.9887},"hosp_30_34":{"mean":8.8732,"sd":1.4014},"hosp_35_39":{"mean":6.1328,"sd":0.9793},"hosp_40_44":{"mean":4.1456,"sd":0.6838},"hosp_45_49":{"mean":2.7755,"sd":0.4803},"hosp_50_54":{"mean":1.9499,"sd":0.3575},"hosp_55_59":{"mean":1.3858,"sd":0.2705},"hosp_60_64":{"mean":0.9503,"sd":0.1977},"hosp_65_69":{"mean":0.5394,"sd":0.1194},"hosp_70_74":{"mean":0.3244,"sd":0.0762},"hosp_75_79":{"mean":0.1677,"sd":0.0416},"hosp_80_84":{"mean":0.0676,"sd":0.0177},"hosp_85_89":{"mean":0.0198,"sd":0.0054},"hosp_90_94":{"mean":0.0034,"sd":0.001},"hosp_95_99":{"mean":0,"sd":0}},"TCD.7.4_1":{"FOI":{"mean":0.0519,"sd":0.0066},"serop9":{"mean":37.2119,"sd":3.6788},"serop9_class":{"mean":37.2119,"sd":3.6788},"hosp_total":{"mean":141.4627,"sd":26.9908},"hosp_0_4":{"mean":22.3511,"sd":5.5833},"hosp_5_9":{"mean":23.8956,"sd":5.4062},"hosp_10_14":{"mean":22.2614,"sd":4.6612},"hosp_15_19":{"mean":18.9608,"sd":3.6838},"hosp_20_24":{"mean":15.0913,"sd":2.734},"hosp_25_29":{"mean":11.4183,"sd":1.9488},"hosp_30_34":{"mean":8.4068,"sd":1.3737},"hosp_35_39":{"mean":5.9904,"sd":0.9571},"hosp_40_44":{"mean":4.1749,"sd":0.6675},"hosp_45_49":{"mean":2.8813,"sd":0.4714},"hosp_50_54":{"mean":2.0859,"sd":0.3557},"hosp_55_59":{"mean":1.5269,"sd":0.2749},"hosp_60_64":{"mean":1.0778,"sd":0.2064},"hosp_65_69":{"mean":0.6293,"sd":0.1287},"hosp_70_74":{"mean":0.389,"sd":0.085},"hosp_75_79":{"mean":0.2065,"sd":0.0482},"hosp_80_84":{"mean":0.0853,"sd":0.0212},"hosp_85_89":{"mean":0.0256,"sd":0.0067},"hosp_90_94":{"mean":0.0044,"sd":0.0012},"hosp_95_99":{"mean":0,"sd":0}},"TCD.8.1_1":{"FOI":{"mean":0.0463,"sd":0.006},"serop9":{"mean":33.9725,"sd":3.5493},"serop9_class":{"mean":33.9725,"sd":3.5493},"hosp_total":{"mean":128.1988,"sd":25.3697},"hosp_0_4":{"mean":19.5687,"sd":4.997},"hosp_5_9":{"mean":20.793,"sd":4.8626},"hosp_10_14":{"mean":19.563,"sd":4.271},"hosp_15_19":{"mean":16.9222,"sd":3.4512},"hosp_20_24":{"mean":13.7128,"sd":2.6159},"hosp_25_29":{"mean":10.5762,"sd":1.896},"hosp_30_34":{"mean":7.9423,"sd":1.3501},"hosp_35_39":{"mean":5.774,"sd":0.9434},"hosp_40_44":{"mean":4.1056,"sd":0.656},"hosp_45_49":{"mean":2.8907,"sd":0.4606},"hosp_50_54":{"mean":2.1345,"sd":0.3457},"hosp_55_59":{"mean":1.5933,"sd":0.2667},"hosp_60_64":{"mean":1.1464,"sd":0.201},"hosp_65_69":{"mean":0.682,"sd":0.1263},"hosp_70_74":{"mean":0.4294,"sd":0.0844},"hosp_75_79":{"mean":0.232,"sd":0.0485},"hosp_80_84":{"mean":0.0976,"sd":0.0217},"hosp_85_89":{"mean":0.0297,"sd":0.007},"hosp_90_94":{"mean":0.0052,"sd":0.0013},"hosp_95_99":{"mean":0,"sd":0}},"TCD.8.2_1":{"FOI":{"mean":0.0407,"sd":0.0074},"serop9":{"mean":30.5132,"sd":4.6655},"serop9_class":{"mean":30.5132,"sd":4.6655},"hosp_total":{"mean":113.7519,"sd":27.6594},"hosp_0_4":{"mean":16.9223,"sd":5.1557},"hosp_5_9":{"mean":17.8166,"sd":5.2054},"hosp_10_14":{"mean":16.859,"sd":4.6711},"hosp_15_19":{"mean":14.7523,"sd":3.8296},"hosp_20_24":{"mean":12.1281,"sd":2.9251},"hosp_25_29":{"mean":9.5057,"sd":2.1188},"hosp_30_34":{"mean":7.2621,"sd":1.4929},"hosp_35_39":{"mean":5.3749,"sd":1.0211},"hosp_40_44":{"mean":3.893,"sd":0.6884},"hosp_45_49":{"mean":2.793,"sd":0.4662},"hosp_50_54":{"mean":2.1022,"sd":0.3382},"hosp_55_59":{"mean":1.5999,"sd":0.2547},"hosp_60_64":{"mean":1.1738,"sd":0.1902},"hosp_65_69":{"mean":0.7121,"sd":0.1204},"hosp_70_74":{"mean":0.4573,"sd":0.0822},"hosp_75_79":{"mean":0.252,"sd":0.0487},"hosp_80_84":{"mean":0.108,"sd":0.0226},"hosp_85_89":{"mean":0.0336,"sd":0.0076},"hosp_90_94":{"mean":0.006,"sd":0.0015},"hosp_95_99":{"mean":0,"sd":0}},"TCD.8.3_1":{"FOI":{"mean":0.0446,"sd":0.0073},"serop9":{"mean":32.9125,"sd":4.4562},"serop9_class":{"mean":32.9125,"sd":4.4562},"hosp_total":{"mean":123.6841,"sd":27.3811},"hosp_0_4":{"mean":18.7707,"sd":5.3123},"hosp_5_9":{"mean":19.8877,"sd":5.2931},"hosp_10_14":{"mean":18.7309,"sd":4.6853},"hosp_15_19":{"mean":16.2455,"sd":3.7887},"hosp_20_24":{"mean":13.2112,"sd":2.8576},"hosp_25_29":{"mean":10.2314,"sd":2.0493},"hosp_30_34":{"mean":7.7185,"sd":1.4358},"hosp_35_39":{"mean":5.639,"sd":0.9825},"hosp_40_44":{"mean":4.0307,"sd":0.6679},"hosp_45_49":{"mean":2.8536,"sd":0.4594},"hosp_50_54":{"mean":2.1193,"sd":0.3403},"hosp_55_59":{"mean":1.5914,"sd":0.2616},"hosp_60_64":{"mean":1.1522,"sd":0.1984},"hosp_65_69":{"mean":0.6899,"sd":0.1265},"hosp_70_74":{"mean":0.4372,"sd":0.0862},"hosp_75_79":{"mean":0.2379,"sd":0.0507},"hosp_80_84":{"mean":0.1007,"sd":0.0233},"hosp_85_89":{"mean":0.0309,"sd":0.0077},"hosp_90_94":{"mean":0.0055,"sd":0.0015},"hosp_95_99":{"mean":0,"sd":0}},"TCD.9.1_1":{"FOI":{"mean":0.0268,"sd":0.0086},"serop9":{"mean":21.1714,"sd":6.1523},"serop9_class":{"mean":21.1714,"sd":6.1523},"hosp_total":{"mean":75.027,"sd":30.1707},"hosp_0_4":{"mean":10.6541,"sd":4.7451},"hosp_5_9":{"mean":10.843,"sd":4.8909},"hosp_10_14":{"mean":10.3191,"sd":4.5867},"hosp_15_19":{"mean":9.2343,"sd":3.9834},"hosp_20_24":{"mean":7.8301,"sd":3.2475},"hosp_25_29":{"mean":6.3606,"sd":2.5206},"hosp_30_34":{"mean":5.0515,"sd":1.9041},"hosp_35_39":{"mean":3.894,"sd":1.3914},"hosp_40_44":{"mean":2.9412,"sd":0.9937},"hosp_45_49":{"mean":2.2024,"sd":0.7024},"hosp_50_54":{"mean":1.731,"sd":0.5205},"hosp_55_59":{"mean":1.376,"sd":0.3902},"hosp_60_64":{"mean":1.0547,"sd":0.2823},"hosp_65_69":{"mean":0.6685,"sd":0.1693},"hosp_70_74":{"mean":0.4484,"sd":0.1079},"hosp_75_79":{"mean":0.2581,"sd":0.0594},"hosp_80_84":{"mean":0.1156,"sd":0.0256},"hosp_85_89":{"mean":0.0375,"sd":0.0081},"hosp_90_94":{"mean":0.007,"sd":0.0015},"hosp_95_99":{"mean":0,"sd":0}},"TCD.9.2_1":{"FOI":{"mean":0.0121,"sd":0.0062},"serop9":{"mean":10.1639,"sd":5.0448},"serop9_class":{"mean":10.1639,"sd":5.0448},"hosp_total":{"mean":31.6347,"sd":20.1218},"hosp_0_4":{"mean":4.5248,"sd":2.8631},"hosp_5_9":{"mean":4.312,"sd":2.8112},"hosp_10_14":{"mean":4.0288,"sd":2.659},"hosp_15_19":{"mean":3.6262,"sd":2.3963},"hosp_20_24":{"mean":3.1361,"sd":2.06},"hosp_25_29":{"mean":2.6209,"sd":1.7028},"hosp_30_34":{"mean":2.1535,"sd":1.3789},"hosp_35_39":{"mean":1.7241,"sd":1.0852},"hosp_40_44":{"mean":1.3559,"sd":0.8374},"hosp_45_49":{"mean":1.0591,"sd":0.6408},"hosp_50_54":{"mean":0.8694,"sd":0.5147},"hosp_55_59":{"mean":0.7224,"sd":0.4181},"hosp_60_64":{"mean":0.5791,"sd":0.3275},"hosp_65_69":{"mean":0.3839,"sd":0.212},"hosp_70_74":{"mean":0.2694,"sd":0.1453},"hosp_75_79":{"mean":0.1622,"sd":0.0854},"hosp_80_84":{"mean":0.076,"sd":0.039},"hosp_85_89":{"mean":0.0258,"sd":0.0129},"hosp_90_94":{"mean":0.0051,"sd":0.0025},"hosp_95_99":{"mean":0,"sd":0}}}
