{"KEN.1_1":{"FOI":{"mean":0.0142,"sd":0.0035},"serop9":{"mean":60.337,"sd":7.3761}},"KEN.2_1":{"FOI":{"mean":0.019,"sd":0.0042},"serop9":{"mean":51.0325,"sd":7.5511}},"KEN.3_1":{"FOI":{"mean":0.0154,"sd":0.0038},"serop9":{"mean":57.988,"sd":7.7764}},"KEN.4_1":{"FOI":{"mean":0.0102,"sd":0.0051},"serop9":{"mean":70.241,"sd":11.7101}},"KEN.5_1":{"FOI":{"mean":0.0124,"sd":0.0033},"serop9":{"mean":64.4253,"sd":7.2305}},"KEN.6_1":{"FOI":{"mean":0.0109,"sd":0.0035},"serop9":{"mean":67.9731,"sd":8.1618}},"KEN.7_1":{"FOI":{"mean":0.011,"sd":0.0029},"serop9":{"mean":67.6971,"sd":6.887}},"KEN.8_1":{"FOI":{"mean":0.0139,"sd":0.0042},"serop9":{"mean":61.192,"sd":8.6772}},"KEN.9_1":{"FOI":{"mean":0.015,"sd":0.0033},"serop9":{"mean":58.6084,"sd":6.9668}},"KEN.10_1":{"FOI":{"mean":0.0115,"sd":0.0034},"serop9":{"mean":66.6728,"sd":7.6711}},"KEN.11_1":{"FOI":{"mean":0.016,"sd":0.0041},"serop9":{"mean":56.8992,"sd":8.2941}},"KEN.12_1":{"FOI":{"mean":0.017,"sd":0.0037},"serop9":{"mean":54.7712,"sd":7.2559}},"KEN.13_1":{"FOI":{"mean":0.0112,"sd":0.0032},"serop9":{"mean":67.3633,"sd":7.4534}},"KEN.14_1":{"FOI":{"mean":0.0122,"sd":0.0033},"serop9":{"mean":64.9318,"sd":7.1948}},"KEN.15_1":{"FOI":{"mean":0.0091,"sd":0.003},"serop9":{"mean":72.42,"sd":7.3276}},"KEN.16_1":{"FOI":{"mean":0.0172,"sd":0.0042},"serop9":{"mean":54.4858,"sd":8.0677}},"KEN.17_1":{"FOI":{"mean":0.0117,"sd":0.0043},"serop9":{"mean":66.2943,"sd":9.5759}},"KEN.18_1":{"FOI":{"mean":0.0127,"sd":0.004},"serop9":{"mean":64.0471,"sd":8.9834}},"KEN.19_1":{"FOI":{"mean":0.0113,"sd":0.0035},"serop9":{"mean":66.9754,"sd":8.0658}},"KEN.20_1":{"FOI":{"mean":0.0183,"sd":0.0048},"serop9":{"mean":52.5621,"sd":9.0339}},"KEN.21_1":{"FOI":{"mean":0.0119,"sd":0.0026},"serop9":{"mean":65.4453,"sd":5.7942}},"KEN.22_1":{"FOI":{"mean":0.0102,"sd":0.0037},"serop9":{"mean":69.7582,"sd":8.8517}},"KEN.23_1":{"FOI":{"mean":0.0112,"sd":0.0038},"serop9":{"mean":67.4492,"sd":8.9701}},"KEN.24_1":{"FOI":{"mean":0.0143,"sd":0.0037},"serop9":{"mean":60.18,"sd":7.6052}},"KEN.25_1":{"FOI":{"mean":0.0151,"sd":0.0036},"serop9":{"mean":58.6268,"sd":7.2395}},"KEN.26_1":{"FOI":{"mean":0.0127,"sd":0.0039},"serop9":{"mean":64.0247,"sd":8.6079}},"KEN.27_1":{"FOI":{"mean":0.0159,"sd":0.0041},"serop9":{"mean":57.0738,"sd":8.144}},"KEN.28_1":{"FOI":{"mean":0.0124,"sd":0.0034},"serop9":{"mean":64.5096,"sd":7.2633}},"KEN.29_1":{"FOI":{"mean":0.0107,"sd":0.0027},"serop9":{"mean":68.4632,"sd":6.4389}},"KEN.30_1":{"FOI":{"mean":0.0109,"sd":0.0038},"serop9":{"mean":68.0921,"sd":8.6355}},"KEN.31_1":{"FOI":{"mean":0.019,"sd":0.0048},"serop9":{"mean":51.1328,"sd":8.6823}},"KEN.32_1":{"FOI":{"mean":0.0168,"sd":0.0036},"serop9":{"mean":55.0108,"sd":7.0909}},"KEN.33_1":{"FOI":{"mean":0.0174,"sd":0.0039},"serop9":{"mean":53.9788,"sd":7.358}},"KEN.34_1":{"FOI":{"mean":0.0171,"sd":0.0042},"serop9":{"mean":54.5913,"sd":8.0972}},"KEN.35_1":{"FOI":{"mean":0.02,"sd":0.0049},"serop9":{"mean":49.4501,"sd":8.6246}},"KEN.36_1":{"FOI":{"mean":0.0147,"sd":0.0034},"serop9":{"mean":59.2739,"sd":7.0893}},"KEN.37_1":{"FOI":{"mean":0.0141,"sd":0.0038},"serop9":{"mean":60.6521,"sd":8.0875}},"KEN.38_1":{"FOI":{"mean":0.0133,"sd":0.0042},"serop9":{"mean":62.699,"sd":9.0863}},"KEN.39_1":{"FOI":{"mean":0.0117,"sd":0.0033},"serop9":{"mean":66.1246,"sd":7.6913}},"KEN.40_1":{"FOI":{"mean":0.0117,"sd":0.0032},"serop9":{"mean":66.1049,"sd":7.5604}},"KEN.41_1":{"FOI":{"mean":0.0122,"sd":0.0038},"serop9":{"mean":64.9207,"sd":8.4209}},"KEN.42_1":{"FOI":{"mean":0.0167,"sd":0.0039},"serop9":{"mean":55.4418,"sd":7.7284}},"KEN.43_1":{"FOI":{"mean":0.0178,"sd":0.0039},"serop9":{"mean":53.2118,"sd":7.3659}},"KEN.44_1":{"FOI":{"mean":0.0167,"sd":0.0038},"serop9":{"mean":55.2695,"sd":7.5118}},"KEN.45_1":{"FOI":{"mean":0.012,"sd":0.0043},"serop9":{"mean":65.614,"sd":9.5968}},"KEN.46_1":{"FOI":{"mean":0.0129,"sd":0.0034},"serop9":{"mean":63.376,"sd":7.3666}},"KEN.47_1":{"FOI":{"mean":0.013,"sd":0.0035},"serop9":{"mean":63.0671,"sd":7.5363}}}
